{
  "folder": "[Gmail]/All Mail",
  "date_token": "2026-03-24T01:11:09+00:00",
  "participants": [
    "starworks5@gmail.com",
    "store-news@amazon.com"
  ],
  "attachment_count": 0,
  "subject": "Today’s deals, curated for you",
  "from": "\"Amazon.com\" <store-news@amazon.com>",
  "to": "starworks5@gmail.com",
  "cc": "",
  "date": "2026-03-24T01:11:09+00:00",
  "body_text": "\r\n  \r\nToday's Deals https://www.amazon.com/deals\r\n\r\n\r\nDeals for you\r\n\r\nJSAUX Displayport Cable\r\n \r\n\r\n\r\nLimited time deal -10% $11.65 List Price: $12.99\r\n            \r\nhttps://www.amazon.com/gp/product/B0CLNRBR5Y/?ref_=pd_ot_dealz_dotd_2p_0_lm&&pd_rd_wg=45Wxi&pd_rd_w=U0Q8x&pf_rd_p=145211a5-a5d7-4fe6-8f8f-9db01f9b61c0&pd_rd_r=ca7be7ae-69bf-4005-96fb-f05b7e1f6a82&content-id=amzn1.sym.145211a5-a5d7-4fe6-8f8f-9db01f9b61c0\r\n\r\nHUANUO Monitor Stand\r\n \r\n\r\n\r\nLimited time deal -21% $54.99 List Price: $69.99\r\n            \r\nhttps://www.amazon.com/gp/product/B07T5SY43L/?ref_=pd_ot_dealz_dotd_2p_1_lm&&pd_rd_wg=45Wxi&pd_rd_w=U0Q8x&pf_rd_p=145211a5-a5d7-4fe6-8f8f-9db01f9b61c0&pd_rd_r=ca7be7ae-69bf-4005-96fb-f05b7e1f6a82&content-id=amzn1.sym.145211a5-a5d7-4fe6-8f8f-9db01f9b61c0\r\n\r\nCarhartt T-Shirt\r\n \r\n\r\n\r\nLimited time deal -33% $32.24 List Price: $47.99\r\n            \r\nhttps://www.amazon.com/gp/product/B0CN7X7JQS/?ref_=pd_ot_dealz_dotd_2p_2_lm&&pd_rd_wg=45Wxi&pd_rd_w=U0Q8x&pf_rd_p=145211a5-a5d7-4fe6-8f8f-9db01f9b61c0&pd_rd_r=ca7be7ae-69bf-4005-96fb-f05b7e1f6a82&content-id=amzn1.sym.145211a5-a5d7-4fe6-8f8f-9db01f9b61c0\r\n\r\nAOOSTAR Mini PC\r\n \r\n\r\n\r\nLimited time deal -15% $313.65 List Price: $369.00\r\n            \r\nhttps://www.amazon.com/gp/product/B0F9WKBFQR/?ref_=pd_ot_dealz_dotd_2p_3_lm&&pd_rd_wg=45Wxi&pd_rd_w=U0Q8x&pf_rd_p=145211a5-a5d7-4fe6-8f8f-9db01f9b61c0&pd_rd_r=ca7be7ae-69bf-4005-96fb-f05b7e1f6a82&content-id=amzn1.sym.145211a5-a5d7-4fe6-8f8f-9db01f9b61c0\r\n\r\nShop now\r\nhttps://www.amazon.com/deals?bubble-id=discounts-collection-for-you\r\n\r\n        \r\n    \r\nBig Spring Sale starts March 25. Shop early deals now\r\n\r\nhttps://www.amazon.com/events/bigspringsale\r\n\r\nExplore deals by category\r\n\r\n\r\nKitchen\r\nhttps://www.amazon.com/deals?bubble-id=kitchen\r\nFashion\r\nhttps://www.amazon.com/deals?bubble-id=fashion\r\nSports & outdoors\r\nhttps://www.amazon.com/deals?bubble-id=sport-outdoors\r\nHome\r\nhttps://www.amazon.com/deals?bubble-id=home\r\nShop all https://www.amazon.com/deals\r\n\r\nMost-loved deals for you\r\n\r\nBEGRIM Cat Toy Pointer\r\n \r\n\r\n\r\nLimited time deal -10% $6.29 Typical price: $6.99\r\n            \r\nhttps://www.amazon.com/gp/product/B09TFNQM7Z/?ref_=pd_ot_dealz_cml_2p_0_lm&&pd_rd_wg=nqoF0&pd_rd_w=qQr2O&pf_rd_p=a8d0e2f2-4440-4d65-ab3e-ecdf4be36c39&pd_rd_r=a40c2ef2-764a-4791-8cf8-7ad898c9710c&content-id=amzn1.sym.a8d0e2f2-4440-4d65-ab3e-ecdf4be36c39\r\n\r\nYes4All Foam Roller\r\n \r\n\r\n\r\nLimited time deal -10% $13.59 List Price: $15.11\r\n            \r\nhttps://www.amazon.com/gp/product/B01LWPQ4D6/?ref_=pd_ot_dealz_cml_2p_1_lm&&pd_rd_wg=nqoF0&pd_rd_w=qQr2O&pf_rd_p=a8d0e2f2-4440-4d65-ab3e-ecdf4be36c39&pd_rd_r=a40c2ef2-764a-4791-8cf8-7ad898c9710c&content-id=amzn1.sym.a8d0e2f2-4440-4d65-ab3e-ecdf4be36c39\r\n\r\nZojirushi Rice Cooker and Warmer\r\n \r\n\r\n\r\nLimited time deal -18% $191.99 List Price: $235.00\r\n            \r\nhttps://www.amazon.com/gp/product/B00007J5U7/?ref_=pd_ot_dealz_cml_2p_2_lm&&pd_rd_wg=nqoF0&pd_rd_w=qQr2O&pf_rd_p=a8d0e2f2-4440-4d65-ab3e-ecdf4be36c39&pd_rd_r=a40c2ef2-764a-4791-8cf8-7ad898c9710c&content-id=amzn1.sym.a8d0e2f2-4440-4d65-ab3e-ecdf4be36c39\r\n\r\ngianotter Desk Organizers and Accessories\r\n \r\n\r\n\r\nLimited time deal -27% $21.98 List Price: $29.99\r\n            \r\nhttps://www.amazon.com/gp/product/B0BWTPH7L1/?ref_=pd_ot_dealz_cml_2p_3_lm&&pd_rd_wg=nqoF0&pd_rd_w=qQr2O&pf_rd_p=a8d0e2f2-4440-4d65-ab3e-ecdf4be36c39&pd_rd_r=a40c2ef2-764a-4791-8cf8-7ad898c9710c&content-id=amzn1.sym.a8d0e2f2-4440-4d65-ab3e-ecdf4be36c39\r\n\r\nShop now\r\nhttps://www.amazon.com/deals?bubble-id=deals-collection-cml\r\n\r\n        \r\n    \r\nShop deals by price\r\n\r\n\r\n\r\nhttps://www.amazon.com/deals?discounts-widget=%2522%257B%255C%2522state%255C%2522%253A%257B%255C%2522rangeRefinementFilters%255C%2522%253A%257B%255C%2522price%255C%2522%253A%257B%255C%2522min%255C%2522%253A0%252C%255C%2522max%255C%2522%253A10%257D%257D%257D%252C%255C%2522version%255C%2522%253A1%257D%2522&promotionsSearchLastSeenAsin=B0B6CMT476&promotionsSearchStartIndex=0&promotionsSearchPageSize=60\r\n\r\nhttps://www.amazon.com/deals?discounts-widget=%2522%257B%255C%2522state%255C%2522%253A%257B%255C%2522rangeRefinementFilters%255C%2522%253A%257B%255C%2522price%255C%2522%253A%257B%255C%2522min%255C%2522%253A0%252C%255C%2522max%255C%2522%253A20%257D%257D%257D%252C%255C%2522version%255C%2522%253A1%257D%2522\r\n\r\nhttps://www.amazon.com/deals?discounts-widget=%2522%257B%255C%2522state%255C%2522%253A%257B%255C%2522rangeRefinementFilters%255C%2522%253A%257B%255C%2522price%255C%2522%253A%257B%255C%2522min%255C%2522%253A0%252C%255C%2522max%255C%2522%253A30%257D%257D%257D%252C%255C%2522version%255C%2522%253A1%257D%2522\r\nUpdate your preferences https://www.amazon.com/gp/cpc/homepage?ref_=pe_ob_ftr_comm_prfs\r\nUnsubscribe https://www.amazon.com/gp/gss/o/10Nt6CRxlYLKHVArDD0tYCvrBz7X8eJGyaFUiO4DHMTzSuM3sj9g6iHGOh-hTCndJ\r\n©2026 Amazon.com, Inc. or its affiliates. Amazon and all related marks are trademarks of Amazon.com, Inc. or its affiliates, Amazon.com 410 Terry Avenue N., Seattle, WA 98109. Product prices and availability are subject to change. Ref: 1365358730.\r\n\r\nPrivacy Notice https://www.amazon.com/gp/help/customer/display.html?nodeId=468496\r\nAmazon.com",
  "body_html": "<!doctype html><html lang=\"en\" dir=\"auto\" xmlns=\"http://www.w3.org/1999/xhtml\" xmlns:v=\"urn:schemas-microsoft-com:vml\" xmlns:o=\"urn:schemas-microsoft-com:office:office\"><head><title></title><!--[if !mso]><!--><meta http-equiv=\"X-UA-Compatible\" content=\"IE=edge\"><!--<![endif]--><meta http-equiv=\"Content-Type\" content=\"text/html; charset=UTF-8\"><meta name=\"viewport\" content=\"width=device-width,initial-scale=1\"><style type=\"text/css\">#outlook a{padding:0}body{margin:0;padding:0;-webkit-text-size-adjust:100%;-ms-text-size-adjust:100%}table,td{border-collapse:collapse;mso-table-lspace:0pt;mso-table-rspace:0pt}img{border:0;height:auto;line-height:100%;outline:0;text-decoration:none;-ms-interpolation-mode:bicubic}p{display:block;margin:13px 0}</style><!--[if mso]>\r\n    <noscript>\r\n    <xml>\r\n    <o:OfficeDocumentSettings>\r\n      <o:AllowPNG/>\r\n      <o:PixelsPerInch>96</o:PixelsPerInch>\r\n    </o:OfficeDocumentSettings>\r\n    </xml>\r\n    </noscript>\r\n    <![endif]--><!--[if lte mso 11]>\r\n    <style type=\"text/css\">.mj-outlook-group-fix{width:100%!important}</style>\r\n    <![endif]--><style type=\"text/css\">@media (prefers-color-scheme:dark){.rio-header-590,.rio-header-590 *{\r\n            color: #FFFFFF !important;\r\n            }}@media (prefers-color-scheme:dark){.rio-text-897{\r\n            color: #FFFFFF;\r\n            }}@media (prefers-color-scheme:dark){.rio-button-1490{\r\n          color: #565959 !important;\r\n          background: #FEFEFE !important;\r\n          border-color: #D5D9D9 !important;\r\n          }.rio-button-cta-secondary{\r\n          background: #FEFEFE !important;\r\n          }}[data-ogsc] .rio-button-1490{\r\n        color: #565959 !important;\r\n        background: #FEFEFE !important;\r\n        border-color: #D5D9D9 !important;\r\n        }[data-ogsc] .rio-button-cta-secondary{\r\n        background: #FEFEFE !important;\r\n        }@media (prefers-color-scheme:dark){.rio-button-1491{\r\n          color: #0F1111 !important;\r\n          background: #FFD916 !important;\r\n          border-color: #FCD200 !important;\r\n          }.rio-button-cta-primary{\r\n          background: #FFD916 !important;\r\n          }}[data-ogsc] .rio-button-1491{\r\n        color: #0F1111 !important;\r\n        background: #FFD916 !important;\r\n        border-color: #FCD200 !important;\r\n        }[data-ogsc] .rio-button-cta-primary{\r\n        background: #FFD916 !important;\r\n        }@media (prefers-color-scheme:dark){.rio-text-898{\r\n            color: #FFFFFF;\r\n            }}@media (prefers-color-scheme:dark){.rio-text-899{\r\n            color: #FFFFFF;\r\n            }}@media (prefers-color-scheme:dark){.rio-text-900{\r\n            color: #FFFFFF;\r\n            }}@media (prefers-color-scheme:dark){.rio-text-901{\r\n            color: #FFFFFF;\r\n            }}@media (prefers-color-scheme:dark){.rio-header-591,.rio-header-591 *{\r\n            color: #FFFFFF !important;\r\n            }}@media (prefers-color-scheme:dark){.rio-button-1492{\r\n          color: #0F1111 !important;\r\n          background: #FFD916 !important;\r\n          border-color: #FCD200 !important;\r\n          }.rio-button-cta-primary{\r\n          background: #FFD916 !important;\r\n          }}[data-ogsc] .rio-button-1492{\r\n        color: #0F1111 !important;\r\n        background: #FFD916 !important;\r\n        border-color: #FCD200 !important;\r\n        }[data-ogsc] .rio-button-cta-primary{\r\n        background: #FFD916 !important;\r\n        }@media (prefers-color-scheme:dark){.rio-header-592,.rio-header-592 *{\r\n            color: #FFFFFF !important;\r\n            }}@media (prefers-color-scheme:dark){.rio-text-902{\r\n            color: #FFFFFF;\r\n            }}@media (prefers-color-scheme:dark){.rio-button-1493{\r\n          color: #565959 !important;\r\n          background: #FEFEFE !important;\r\n          border-color: #D5D9D9 !important;\r\n          }.rio-button-cta-secondary{\r\n          background: #FEFEFE !important;\r\n          }}[data-ogsc] .rio-button-1493{\r\n        color: #565959 !important;\r\n        background: #FEFEFE !important;\r\n        border-color: #D5D9D9 !important;\r\n        }[data-ogsc] .rio-button-cta-secondary{\r\n        background: #FEFEFE !important;\r\n        }@media (prefers-color-scheme:dark){.rio-button-1494{\r\n          color: #0F1111 !important;\r\n          background: #FFD916 !important;\r\n          border-color: #FCD200 !important;\r\n          }.rio-button-cta-primary{\r\n          background: #FFD916 !important;\r\n          }}[data-ogsc] .rio-button-1494{\r\n        color: #0F1111 !important;\r\n        background: #FFD916 !important;\r\n        border-color: #FCD200 !important;\r\n        }[data-ogsc] .rio-button-cta-primary{\r\n        background: #FFD916 !important;\r\n        }@media (prefers-color-scheme:dark){.rio-text-903{\r\n            color: #FFFFFF;\r\n            }}@media (prefers-color-scheme:dark){.rio-text-904{\r\n            color: #FFFFFF;\r\n            }}@media (prefers-color-scheme:dark){.rio-header-593,.rio-header-593 *{\r\n            color: #FFFFFF !important;\r\n            }}@media (prefers-color-scheme:dark){.rio-text-905{\r\n            color: #FFFFFF;\r\n            }}@media (prefers-color-scheme:dark){.rio-button-1495{\r\n          color: #565959 !important;\r\n          background: #FEFEFE !important;\r\n          border-color: #D5D9D9 !important;\r\n          }.rio-button-cta-secondary{\r\n          background: #FEFEFE !important;\r\n          }}[data-ogsc] .rio-button-1495{\r\n        color: #565959 !important;\r\n        background: #FEFEFE !important;\r\n        border-color: #D5D9D9 !important;\r\n        }[data-ogsc] .rio-button-cta-secondary{\r\n        background: #FEFEFE !important;\r\n        }@media (prefers-color-scheme:dark){.rio-button-1496{\r\n          color: #0F1111 !important;\r\n          background: #FFD916 !important;\r\n          border-color: #FCD200 !important;\r\n          }.rio-button-cta-primary{\r\n          background: #FFD916 !important;\r\n          }}[data-ogsc] .rio-button-1496{\r\n        color: #0F1111 !important;\r\n        background: #FFD916 !important;\r\n        border-color: #FCD200 !important;\r\n        }[data-ogsc] .rio-button-cta-primary{\r\n        background: #FFD916 !important;\r\n        }@media (prefers-color-scheme:dark){.rio-text-906{\r\n            color: #FFFFFF;\r\n            }}@media (prefers-color-scheme:dark){.rio-text-907{\r\n            color: #FFFFFF;\r\n            }}@media (prefers-color-scheme:dark){.rio-text-908{\r\n            color: #FFFFFF;\r\n            }}@media (prefers-color-scheme:dark){.rio-text-909{\r\n            color: #FFFFFF;\r\n            }}@media (prefers-color-scheme:dark){.rio-header-594,.rio-header-594 *{\r\n            color: #FFFFFF !important;\r\n            }}@media (prefers-color-scheme:dark){.rio-text-910{\r\n            color: #FFFFFF;\r\n            }}@media (prefers-color-scheme:dark){.rio-button-1497{\r\n          color: #565959 !important;\r\n          background: #FEFEFE !important;\r\n          border-color: #D5D9D9 !important;\r\n          }.rio-button-cta-secondary{\r\n          background: #FEFEFE !important;\r\n          }}[data-ogsc] .rio-button-1497{\r\n        color: #565959 !important;\r\n        background: #FEFEFE !important;\r\n        border-color: #D5D9D9 !important;\r\n        }[data-ogsc] .rio-button-cta-secondary{\r\n        background: #FEFEFE !important;\r\n        }@media (prefers-color-scheme:dark){.rio-button-1498{\r\n          color: #0F1111 !important;\r\n          background: #FFD916 !important;\r\n          border-color: #FCD200 !important;\r\n          }.rio-button-cta-primary{\r\n          background: #FFD916 !important;\r\n          }}[data-ogsc] .rio-button-1498{\r\n        color: #0F1111 !important;\r\n        background: #FFD916 !important;\r\n        border-color: #FCD200 !important;\r\n        }[data-ogsc] .rio-button-cta-primary{\r\n        background: #FFD916 !important;\r\n        }@media (prefers-color-scheme:dark){.rio-text-911{\r\n            color: #FFFFFF;\r\n            }}@media (prefers-color-scheme:dark){.rio-text-912{\r\n            color: #FFFFFF;\r\n            }}\r\n         .amazon-logo {\r\n            background-color: #FFFFFF!important;\r\n        }\r\n        \r\n        .amazon-navbar-content{\r\n            font-family:Ember,'Amazon Ember',Arial,sans-serif;\r\n            font-size: 14px !important;\r\n            font-weight:700 !important;\r\n            background-color: #FFFFFF!important;\r\n        }\r\n        .amazon-logo.full{padding-left:0!important;padding-right:0!important}.amazon-logo.zeroBorder{border:0;border-collapse:collapse;border-spacing:0}.amazon-logo .full{padding-left:0!important;padding-right:0!important}.amazon-logo .zeroBorder{border:0;border-collapse:collapse;border-spacing:0}.amazon-logo .light-img{background-color:#fff;background-image:linear-gradient(#fff,#fff)}@media (prefers-color-scheme:light){.amazon-logo .light-img{display:block!important}.amazon-logo .dark-img{display:none!important}\r\n            .amazon-navbar-content {\r\n                font-family:Ember,'Amazon Ember',Arial,sans-serif;\r\n                background-color: #FFFFFF!important;\r\n                color:  #0F1111!important;\r\n            }\r\n             }@media (prefers-color-scheme:dark){.amazon-logo{background-color:#181a1a!important} \r\n            .amazon-navbar-content {\r\n                background-color: #161D26 !important;\r\n                color:#FFFFFF!important;\r\n            }\r\n             .amazon-logo .light-img{display:none!important}.amazon-logo .dark-img{display:block!important}}[data-ogsc] .amazon-logo .content{background-color:#181a1a!important}[data-ogsc] .amazon-logo .light-img{display:none!important}[data-ogsc] .amazon-logo .dark-img{display:block!important}@media (prefers-color-scheme:dark){.rio-card,.rio-card-text,.rio-card-text>table,.rio-card>table{background-color:#181a1a!important}}[data-ogsc] .rio-card,[data-ogsc] .rio-card-text,[data-ogsc] .rio-card-text>table,[data-ogsc] .rio-card>table{background-color:#181a1a!important}.rio-card-text p+p{margin-top:1.2em}.rio-header strong{color:#067d62}@media (prefers-color-scheme:dark){.rio-header *{\r\n            color: #FFFFFF !important;\r\n            }.rio-header a{color:#6ed6e6!important}.rio-header strong{color:#13bd96!important}}\r\n        [data-ogsc] .rio-header,\r\n        [data-ogsc] .rio-header * {\r\n          color: #FFFFFF !important;\r\n        }\r\n        [data-ogsc] .rio-header a,[data-ogsc] .rio-header a>*{color:#6ed6e6!important}[data-ogsc] .rio-header strong{color:#13bd96!important}.rio-text strong{color:#067d62}.rio-text img:not([data-emoji]){width:100%;height:auto}@media (prefers-color-scheme:dark){.rio-text *{\r\n            color: #FFFFFF !important;\r\n            }.rio-text a,.rio-text a>*{color:#6ed6e6!important}.rio-text strong{color:#13bd96!important}}[data-ogsc] .rio-text *{\r\n          color: #FFFFFF !important;\r\n          }[data-ogsc] .rio-text a,[data-ogsc] .rio-text a>*{color:#6ed6e6!important}[data-ogsc] .rio-text strong{color:#13bd96!important}@media (prefers-color-scheme:dark){.rio-button *{\r\n          color: #0F1111 !important;\r\n          }}[data-ogsc] .rio-button *{\r\n        color: #0F1111 !important;\r\n        }@media (prefers-color-scheme:dark){.rio-table-grid-td-bg{background:#252626!important}}[data-ogsc] .rio-table-grid-td-bg{background:#252626!important}@media (prefers-color-scheme:dark){.asin-container{background:#252626!important}}[data-ogsc] .asin-container{background:#252626!important}.rio-asin-container-image img{mix-blend-mode:multiply;object-fit:contain}@media (prefers-color-scheme:dark){.rio-asin-container-image img{mix-blend-mode:initial!important}}u+.body .rio-asin-container-image img{mix-blend-mode:initial!important}@media only screen and (min-width:600px){u+.body .rio-asin-container-image img{mix-blend-mode:multiply!important}}[data-ogsc] .rio-asin-container-image img{mix-blend-mode:initial!important}\r\n      @media (prefers-color-scheme: dark) {\r\n          .productHvePrimeDayPrice {\r\n              color: #FFFFFF !important;\r\n          }\r\n          .priceBadge {\r\n              color: #FF8C8C !important;\r\n          },\r\n          .priceDiscount {\r\n              background-color: #FF8C8C !important;\r\n          },\r\n          .productListPrice {\r\n              color: #FFFFFF !important;\r\n          }\r\n      }\r\n      [data-ogsc]  .productListPrice {\r\n          color: #FFFFFF !important;\r\n      }\r\n      [data-ogsc] .productHvePrimeDayPrice {\r\n          color: #FFFFFF !important;\r\n      }\r\n      [data-ogsc] .priceBadge {\r\n          color: #FF8C8C !important;\r\n      } \r\n      [data-ogsc] .priceDiscount {\r\n          background-color: #FF8C8C !important;\r\n      } \r\n      \r\n        @media (prefers-color-scheme: dark) {\r\n            .productHveDiscount {\r\n                color: #FF8C8C !important;\r\n            }\r\n            .productHvePrice {\r\n                color: #FFFFFF !important;\r\n            }\r\n        }\r\n        [data-ogsc]  .productHveDiscount {\r\n            color: #FF8C8C !important;\r\n        }\r\n        [data-ogsc] .productHvePrice {\r\n            color: #FFFFFF !important;\r\n        }\r\n        @media (prefers-color-scheme:dark){.anchorText a{color:#fff!important;text-decoration:underline #FFFFFF!important}}[data-ogsc] .anchorText a{color:#fff!important;text-decoration:underline #FFFFFF!important}@media (prefers-color-scheme:dark){.anchorText a{color:#fff!important;text-decoration:underline #FFFFFF!important}}[data-ogsc] .anchorText a{color:#fff!important;text-decoration:underline #FFFFFF!important}\r\n        .footer-text, .footer-card p, .footer-card li {\r\n            color: #494D4D;\r\n        }\r\n        .footer-card p{margin-top:20px}\r\n        .footer-card a {\r\n            color: #007185 !important;\r\n            text-decoration: none !important;\r\n        }\r\n        @media (prefers-color-scheme:dark){\r\n            .footer-card {\r\n                background-color: #303333 !important;\r\n            }\r\n            \r\n            .footer-card a {\r\n                color: #6ED6E6 !important;\r\n            }\r\n            \r\n            .footer-text, .footer-card p, .footer-card li {\r\n                color: #C8CCCC !important;\r\n            }\r\n            .lightFooterImg{display:none!important}.darkFooterImg{display:block!important}}[data-ogsb] .footer-card{background-color:#303333!important}\r\n        [data-ogsc] .footer-card a {\r\n            color: #6ED6E6 !important;\r\n        }\r\n        [data-ogsc] .footer-card li,[data-ogsc] .footer-card p,[data-ogsc] .footer-text{color:#c8cccc!important}[data-ogsc] .lightFooterImg{display:none!important}[data-ogsc] .darkFooterImg{display:block!important}</style><style type=\"text/css\">@font-face{font-family:Ember;font-weight:700;src:local(\"Ember\"),url(https://m.media-amazon.com/images/G/01/outbound/AmazonEmber_Bd._CB1515450239_.WOFF) format(\"woff\");mso-generic-font-family:swiss;mso-font-alt:\"Arial\"}@font-face{font-family:Ember;font-weight:600;src:local(\"Ember\"),url(https://m.media-amazon.com/images/G/01/outbound/AmazonEmber_Bd._CB1515450239_.WOFF) format(\"woff\");mso-generic-font-family:swiss;mso-font-alt:\"Arial\"}@font-face{font-family:Ember;font-weight:500;src:local(\"Ember\"),url(https://m.media-amazon.com/images/G/01/outbound/AmazonEmber_Md._CB1515450239_.WOFF) format(\"woff\");mso-generic-font-family:swiss;mso-font-alt:\"Arial\"}@font-face{font-family:Ember;font-weight:400;font-style:normal;src:local(\"Ember\"),url(https://m.media-amazon.com/images/G/01/outbound/AmazonEmber_Rg._CB1515450239_.WOFF) format(\"woff\");mso-generic-font-family:swiss;mso-font-alt:\"Arial\"}@font-face{font-family:Ember;font-weight:200;src:local(\"Ember\"),url(https://m.media-amazon.com/images/G/01/outbound/AmazonEmber_Lt._CB1515450239_.WOFF) format(\"woff\");mso-generic-font-family:swiss;mso-font-alt:\"Arial\"}@font-face{font-family:\"Amazon Ember\";font-weight:700;src:local(\"Amazon Ember\"),url(https://m.media-amazon.com/images/G/01/outbound/AmazonEmber_Bd._CB1515450239_.WOFF) format(\"woff\");mso-generic-font-family:swiss;mso-font-alt:\"Arial\"}@font-face{font-family:\"Amazon Ember\";font-weight:600;src:local(\"Amazon Ember\"),url(https://m.media-amazon.com/images/G/01/outbound/AmazonEmber_Bd._CB1515450239_.WOFF) format(\"woff\");mso-generic-font-family:swiss;mso-font-alt:\"Arial\"}@font-face{font-family:\"Amazon Ember\";font-weight:500;src:local(\"Amazon Ember\"),url(https://m.media-amazon.com/images/G/01/outbound/AmazonEmber_Md._CB1515450239_.WOFF) format(\"woff\");mso-generic-font-family:swiss;mso-font-alt:\"Arial\"}@font-face{font-family:\"Amazon Ember\";font-style:normal;font-weight:400;src:local(\"Amazon Ember\"),url(https://m.media-amazon.com/images/G/01/outbound/AmazonEmber_Rg._CB1515450239_.WOFF) format(\"woff\");mso-generic-font-family:swiss;mso-font-alt:\"Arial\"}@font-face{font-family:\"Amazon Ember\";font-weight:200;src:local(\"Amazon Ember\"),url(https://m.media-amazon.com/images/G/01/outbound/AmazonEmber_Lt._CB1515450239_.WOFF) format(\"woff\");mso-generic-font-family:swiss;mso-font-alt:\"Arial\"}*{font-family:Ember,'Amazon Ember',Arial,sans-serif;border-spacing:0;margin:0;padding:0}ol,ul{margin-left:32px!important}[data-ogsc] :root{--body-bg:#181A1A;--body-color:#ffffff}.rootContent{background:#fff!important}.fonts,.sans,h1,h2,h3,h4,h5,li,p,table,td,th{color:#0f1111}a{color:#007185;text-decoration:none}@media screen and (max-width:599px){.mobile-only{display:initial!important}.desktop-only{display:none!important;mso-hide:all!important}}@media screen and (min-width:600px){.mobile-only{display:none!important;mso-hide:all!important}}@media (prefers-color-scheme:light){:root{--body-bg:#ffffff;--body-color:#000000}}@media (prefers-color-scheme:dark){:root{--body-bg:#181A1A;--body-color:#ffffff}body{background-color:#181a1a!important}.fonts,.sans,h1,h2,h3,h4,h5,li,p,table,td,th{color:#fff}a{color:#6ed6e6}.rootContent,.rootContent>table{background:#181a1a!important}}[data-ogsc] .fonts,[data-ogsc] .sans,[data-ogsc] h1,[data-ogsc] h2,[data-ogsc] h3,[data-ogsc] h4,[data-ogsc] h5,[data-ogsc] li,[data-ogsc] p{color:#fff}[data-ogsc] a{color:#6ed6e6}[data-ogsc] .rootContent,[data-ogsc] .rootContent>table{background:#181a1a!important}body{background-color:var(--body-bg)!important;color:var(--body-color)!important;margin:0!important;padding:0}body>img{position:absolute}table{border-spacing:0}h3,h4,h5,p,table th{font-weight:400;margin:0;padding:0}td{padding:0}img{border:0}a,span,td{word-break:break-word!important}.button{background-color:#ffd814;color:#0f1111!important;border-radius:24px;padding:1px 16px;display:inline-block;box-shadow:1px 2px 4px rgba(153,153,153,.2);font-size:13px;line-height:29px;white-space:nowrap;text-decoration:none;margin-top:4px}.box-shadow a{box-shadow:1px 2px 4px rgba(153,153,153,.2)}a,body,table,td{-ms-text-size-adjust:100%;-webkit-text-size-adjust:100%}.appleBody a,.appleFooter a{color:#007185!important;text-decoration:none}a[x-apple-data-detectors]{color:#007185!important;font-family:inherit!important;font-size:inherit!important;font-weight:inherit!important;line-height:inherit!important}u+#body a{color:#007185!important;font-family:inherit!important;font-size:inherit!important;font-weight:inherit!important;line-height:inherit!important}#MessageViewBody a{color:#007185!important;font-family:inherit!important;font-size:inherit!important;font-weight:inherit!important;line-height:inherit!important}</style><meta content=\"text/html; charset=UTF-8\" http-equiv=\"Content-Type\"><meta content=\"telephone=no\" name=\"format-detection\"><meta content=\"width=device-width,initial-scale=1;user-scalable=no;\" name=\"viewport\"><meta content=\"IE=9; IE=8; IE=7; IE=EDGE\" http-equiv=\"X-UA-Compatible\"><meta name=\"x-apple-disable-message-reformatting\"><meta content=\"light dark\" name=\"color-scheme\"><meta content=\"light dark\" name=\"supported-color-schemes\"><!--\r\n              \r\n              \r\n              \r\n              --><style type=\"text/css\">.productListPrice{color:#565959}.productDiscount{color:#cc0c39}.productPrice{color:#0f1111}@media (prefers-color-scheme:dark){.productListPrice{color:#fff!important}.productDiscount{color:#ff8c8c!important}.productPrice{color:#fff!important}}[data-ogsc] .productListPrice{color:#fff!important}[data-ogsc] .productDiscount{color:#ff8c8c!important}[data-ogsc] .productPrice{color:#fff!important}</style><style type=\"text/css\">.dealBadge{background-color:#cc0c39;color:#fff}.dealText{color:#cc0c39}@media (prefers-color-scheme:dark){.dealBadge{background-color:#ff8c8c!important;color:#000!important}.dealText{color:#ff8c8c!important}}[data-ogsc] .dealBadge{background-color:#ff8c8c!important;color:#000!important}[data-ogsc] .dealText{color:#ff8c8c!important}</style><!--[if gte mso 9]>\r\n    <xml>\r\n        <o:OfficeDocumentSettings>\r\n            <o:AllowPNG />\r\n            <o:PixelsPerInch>96</o:PixelsPerInch>\r\n        </o:OfficeDocumentSettings>\r\n    </xml>\r\n    <style>\r\n        body, h1, h2, h3, h4, table, th, td, p, li, a, .sans, .fonts {\r\n            font-family: Helvetica, Arial, sans-serif !important;\r\n        }\r\n        [data-ogsc] .rootContent, [data-ogsc] .rootContent > table{\r\n          background: #181A1A !important;\r\n        }\r\n    </style>\r\n    <![endif]--></head><body class=\"body\" style=\"word-spacing:normal;\"><img width=\"1\" height=\"1\" src=\"https://www.amazon.com/gp/r.html?C=3BEF3T114MSHJ&K=PLA15W5PCRNT&M=urn:rtn:msg:202603240111072e6e5e7d64a94aec9e4b685effc0p0na&R=2Y84369GGEFRW&T=O&U=https%3A%2F%2Fimages-na.ssl-images-amazon.com%2Fimages%2FG%2F01%2Fnav%2Ftransp.gif&H=AMACZIDI3MMBB4UPT1BG6JV4BDYA&ref_=pe_101622500_1365358730_opens\" alt=\"\" /><div style=\"display:none;font-size:1px;color:#ffffff;line-height:1px;max-height:0px;max-width:0px;opacity:0;overflow:hidden;\">Shop early Big Spring Sale deals & more&#847; &zwnj; &nbsp; &#8199; &shy;&#847; &zwnj; &nbsp; &#8199; &shy;&#847; &zwnj; &nbsp; &#8199; &shy;&#847; &zwnj; &nbsp; &#8199; &shy;&#847; &zwnj; &nbsp; &#8199; &shy;&#847; &zwnj; &nbsp; &#8199; &shy;&#847; &zwnj; &nbsp; &#8199; &shy;&#847; &zwnj; &nbsp; &#8199; &shy;&#847; &zwnj; &nbsp; &#8199; &shy;&#847; &zwnj; &nbsp; &#8199; &shy;&#847; &zwnj; &nbsp; &#8199; &shy;&#847; &zwnj; &nbsp; &#8199; &shy;&#847; &zwnj; &nbsp; &#8199; &shy;&#847; &zwnj; &nbsp; &#8199; &shy;&#847; &zwnj; &nbsp; &#8199; &shy;&#847; &zwnj; &nbsp; &#8199; &shy;&#847; &zwnj; &nbsp; &#8199; &shy;&#847; &zwnj; &nbsp; &#8199; &shy;&#847; &zwnj; &nbsp; &#8199; &shy;&#847; &zwnj; &nbsp; &#8199; &shy;&#847; &zwnj; &nbsp; &#8199; &shy;&#847; &zwnj; &nbsp; &#8199; &shy;&#847; &zwnj; &nbsp; &#8199; &shy;&#847; &zwnj; &nbsp; &#8199; &shy;&#847; &zwnj; &nbsp; &#8199; &shy;&#847; &zwnj; &nbsp; &#8199; &shy;&#847; &zwnj; &nbsp; &#8199; &shy;&#847; &zwnj; &nbsp; &#8199; &shy;&#847; &zwnj; &nbsp; &#8199; &shy;&#847; &zwnj; &nbsp; &#8199; &shy;&#847; &zwnj; &nbsp; &#8199; &shy;&#847; &zwnj; &nbsp; &#8199; &shy;&#847; &zwnj; &nbsp; &#8199; &shy;&#847; &zwnj; &nbsp; &#8199; &shy;&#847; &zwnj; &nbsp; &#8199; &shy;&#847; &zwnj; &nbsp; &#8199; &shy;&#847; &zwnj; &nbsp; &#8199; &shy;&#847; &zwnj; &nbsp; &#8199; &shy;&#847; &zwnj; &nbsp; &#8199; &shy;&#847; &zwnj; &nbsp; &#8199; &shy;&#847; &zwnj; &nbsp; &#8199; &shy;&#847; &zwnj; &nbsp; &#8199; &shy;&#847; &zwnj; &nbsp; &#8199; &shy;&#847; &zwnj; &nbsp; &#8199; &shy;&#847; &zwnj; &nbsp; &#8199; &shy;&#847; &zwnj; &nbsp; &#8199; &shy;&#847; &zwnj; &nbsp; &#8199; &shy;&#847; &zwnj; &nbsp; &#8199; &shy;&#847; &zwnj; &nbsp; &#8199; &shy;&#847; &zwnj; &nbsp; &#8199; &shy;&#847; &zwnj; &nbsp; &#8199; &shy;&#847; &zwnj; &nbsp; &#8199; &shy;&#847; &zwnj; &nbsp; &#8199; &shy;&#847; &zwnj; &nbsp; &#8199; &shy;&#847; &zwnj; &nbsp; &#8199; &shy;&#847; &zwnj; &nbsp; &#8199; &shy;&#847; &zwnj; &nbsp; &#8199; &shy;&#847; &zwnj; &nbsp; &#8199; &shy;&#847; &zwnj; &nbsp; &#8199; &shy;&#847; &zwnj; &nbsp; &#8199; &shy;&#847; &zwnj; &nbsp; &#8199; &shy;&#847; &zwnj; &nbsp; &#8199; &shy;&#847; &zwnj; &nbsp; &#8199; &shy;&#847; &zwnj; &nbsp; &#8199; &shy;&#847; &zwnj; &nbsp; &#8199; &shy;&#847; &zwnj; &nbsp; &#8199; &shy;&#847; &zwnj; &nbsp; &#8199; &shy;&#847; &zwnj; &nbsp; &#8199; &shy;&#847; &zwnj; &nbsp; &#8199; &shy;&#847; &zwnj; &nbsp; &#8199; &shy;&#847; &zwnj; &nbsp; &#8199; &shy;&#847; &zwnj; &nbsp; &#8199; &shy;&#847; &zwnj; &nbsp; &#8199; &shy;&#847; &zwnj; &nbsp; &#8199; &shy;&#847; &zwnj; &nbsp; &#8199; &shy;&#847; &zwnj; &nbsp; &#8199; &shy;&#847; &zwnj; &nbsp; &#8199; &shy;&#847; &zwnj; &nbsp; &#8199; &shy;&#847; &zwnj; &nbsp; &#8199; &shy;&#847; &zwnj; &nbsp; &#8199; &shy;&#847; &zwnj; &nbsp; &#8199; &shy;&#847; &zwnj; &nbsp; &#8199; &shy;&#847; &zwnj; &nbsp; &#8199; &shy;&#847; &zwnj; &nbsp; &#8199; &shy;&#847; &zwnj; &nbsp; &#8199; &shy;&#847; &zwnj; &nbsp; &#8199; &shy;&#847; &zwnj; &nbsp; &#8199; &shy;&#847; &zwnj; &nbsp; &#8199; &shy;&#847; &zwnj; &nbsp; &#8199; &shy;&#847; &zwnj; &nbsp; &#8199; &shy;&#847; &zwnj; &nbsp; &#8199; &shy;&#847; &zwnj; &nbsp; &#8199; &shy;&#847; &zwnj; &nbsp; &#8199; &shy;&#847; &zwnj; &nbsp; &#8199; &shy;&#847; &zwnj; &nbsp; &#8199; &shy;&#847; &zwnj; &nbsp; &#8199; &shy;&#847; &zwnj; &nbsp; &#8199; &shy;&#847; &zwnj; &nbsp; &#8199; &shy;&#847; &zwnj; &nbsp; &#8199; &shy;&#847; &zwnj; &nbsp; &#8199; &shy;&#847; &zwnj; &nbsp; &#8199; &shy;&#847; &zwnj; &nbsp; &#8199; &shy;&#847; &zwnj; &nbsp; &#8199; &shy;&#847; &zwnj; &nbsp; &#8199; &shy;&#847; &zwnj; &nbsp; &#8199; &shy;&#847; &zwnj; &nbsp; &#8199; &shy;&#847; &zwnj; &nbsp; &#8199; &shy;&#847; &zwnj; &nbsp; &#8199; &shy;&#847; &zwnj; &nbsp; &#8199; &shy;&#847; &zwnj; &nbsp; &#8199; &shy;&#847; &zwnj; &nbsp; &#8199; &shy;&#847; &zwnj; &nbsp; &#8199; &shy;&#847; &zwnj; &nbsp; &#8199; &shy;&#847; &zwnj; &nbsp; &#8199; &shy;&#847; &zwnj; &nbsp; &#8199; &shy;&#847; &zwnj; &nbsp; &#8199; &shy;&#847; &zwnj; &nbsp; &#8199; &shy;&#847; &zwnj; &nbsp; &#8199; &shy;&#847; &zwnj; &nbsp; &#8199; &shy;&#847; &zwnj; &nbsp; &#8199; &shy;&#847; &zwnj; &nbsp; &#8199; &shy;&#847; &zwnj; &nbsp; &#8199; &shy;&#847; &zwnj; &nbsp; &#8199; &shy;&#847; &zwnj; &nbsp; &#8199; &shy;&#847; &zwnj; &nbsp; &#8199; &shy;&#847; &zwnj; &nbsp; &#8199; &shy;&#847; &zwnj; &nbsp; &#8199; &shy;&#847; &zwnj; &nbsp; &#8199; &shy;&#847; &zwnj; &nbsp; &#8199; &shy;&#847; &zwnj; &nbsp; &#8199; &shy;&#847; &zwnj; &nbsp; &#8199; &shy;&#847; &zwnj; &nbsp; &#8199; &shy;&#847; &zwnj; &nbsp; &#8199; &shy;&#847; &zwnj; &nbsp; &#8199; &shy;&#847; &zwnj; &nbsp; &#8199; &shy;&#847; &zwnj; &nbsp; &#8199; &shy;&#847; &zwnj; &nbsp; &#8199; &shy;&#847; &zwnj; &nbsp; &#8199; &shy;&#847; &zwnj; &nbsp; &#8199; &shy;&#847; &zwnj; &nbsp; &#8199; &shy;&#847; &zwnj; &nbsp; &#8199; &shy;&#847; &zwnj; &nbsp; &#8199; &shy;&#847; &zwnj; &nbsp; &#8199; &shy;&#847; &zwnj; &nbsp; &#8199; &shy;&#847; &zwnj; &nbsp; &#8199; &shy;&#847; &zwnj; &nbsp; &#8199; &shy;&#847; &zwnj; &nbsp; &#8199; &shy;&#847; &zwnj; &nbsp; &#8199; &shy;&#847; &zwnj; &nbsp; &#8199; &shy;&#847; &zwnj; &nbsp; &#8199; &shy;</div><div class=\"body\" lang=\"en\" dir=\"auto\"> <!--[if mso | IE]><table align=\"center\" border=\"0\" cellpadding=\"0\" cellspacing=\"0\" class=\"rootContent-outlook moduleId-amazonEstablishedLogo-outlook\" role=\"presentation\" style=\"width:600px;\" width=\"600\" bgcolor=\"#ffffff\" ><tr><td style=\"line-height:0px;font-size:0px;mso-line-height-rule:exactly;\"><![endif]--><div class=\"rootContent moduleId-amazonEstablishedLogo\" style=\"background:#ffffff;background-color:#ffffff;margin:0px auto;max-width:600px;\"><table align=\"center\" border=\"0\" cellpadding=\"0\" cellspacing=\"0\" role=\"presentation\" style=\"background:#ffffff;background-color:#ffffff;width:100%;\"><tbody><tr><td style=\"direction:ltr;font-size:0px;padding:0px 0px 0px 0px;text-align:left;\"><!--[if mso | IE]><table role=\"presentation\" border=\"0\" cellpadding=\"0\" cellspacing=\"0\"><![endif]-->    <!-- PRIME LOGO --><!-- ALEXA LOGO --><!-- AMAZON BUSINESS LOGO --><!-- All European Union marketplaces need to use dma compliant logo -->  <!--[if mso | IE]><tr><td align=\"left\" class=\"\" width=\"600px\" ><![endif]-->    <!--[if mso]><table cellpadding=\"0\" cellspacing=\"0\" border=\"0\" role=\"presentation\" width=\"600\" style=\"width:600px\" bgcolor=\"#FFFFFF\"><tr><td><![endif]--><table class=\"amazon-logo\" cellpadding=\"0\" cellspacing=\"0\" border=\"0\" role=\"presentation\" width=\"100%\" bgcolor=\"#FFFFFF\" style=\"width:100%;\" data-sonar-role=\"header\"><tr><td class=\"full zeroborder content\" padding=\"0\">   <a href=\"https://www.amazon.com/gp/r.html?C=3BEF3T114MSHJ&K=PLA15W5PCRNT&M=urn:rtn:msg:202603240111072e6e5e7d64a94aec9e4b685effc0p0na&R=12O3GN0UOHXGK&T=C&U=https%3A%2F%2Fwww.amazon.com%3Fref_%3Dpe_101622500_1365358730_TNL_00_00_IMG_00&H=F6MRKOTLTJLYELLXUG9KELJYRX4A&ref_=pe_101622500_1365358730_TNL_00_00_IMG_00\" target=\"_blank\"><img src=\"https://m.media-amazon.com/images/G/01/outbound/OutboundTemplates/Smile_Logo_Light_Established._BG255,255,255_.png\" height=\"44\" style=\"height:44px;border:0;display:block;max-height:44px;background-color:#ffffff\" class=\"light-img\" alt=\"Amazon\"> <!--[if !mso]><! --><img src=\"https://m.media-amazon.com/images/G/01/outbound/OutboundTemplates/Smile_Logo_Dark_Established.png\" height=\"44\" style=\"height:44px;display:none;border:0;max-height:44px;\" class=\"dark-img\" alt=\"Amazon\"><!--<![endif]--> </a></td><td align=\"right\" style=\"align:right;width:100%;\"><table cellpadding=\"0\" cellspacing=\"0\" border=\"0\" role=\"list\"><tr> <td style=\"padding-top:12px;padding-bottom:12px;padding-right:16px;\" role=\"listitem\"><a href=\"https://www.amazon.com/gp/r.html?C=3BEF3T114MSHJ&K=PLA15W5PCRNT&M=urn:rtn:msg:202603240111072e6e5e7d64a94aec9e4b685effc0p0na&R=9O4958KY1JB0&T=C&U=https%3A%2F%2Fwww.amazon.com%2Fdeals%3Fref_%3Dpe_101622500_1365358730_TNL_00_01_BT_00&H=6KFLDXF78GANPHP1F01HSTK44D4A&ref_=pe_101622500_1365358730_TNL_00_01_BT_00\" target=\"_blank\" class=\"amazon-navbar-content\" style=\"text-decoration: none !important;font-size: 14px !important;font-weight:bold !important;white-space:nowrap;font-family:Ember,'Amazon Ember',Arial,sans-serif; color: #0F1111;\"><strong>Today's Deals</strong></a></td>  <td style=\"padding-top:12px;padding-bottom:12px;padding-right:16px;\" role=\"listitem\"><a href=\"https://www.amazon.com/gp/r.html?C=3BEF3T114MSHJ&K=PLA15W5PCRNT&M=urn:rtn:msg:202603240111072e6e5e7d64a94aec9e4b685effc0p0na&R=18OFF6QS96DH7&T=C&U=https%3A%2F%2Fwww.amazon.com%2Fgp%2Fbuyagain%3Fref_%3Dpe_101622500_1365358730_TNL_00_02_BT_00&H=UOYATP3N2BOW1MUO7QWA0AQIMJYA&ref_=pe_101622500_1365358730_TNL_00_02_BT_00\" target=\"_blank\" class=\"amazon-navbar-content\" style=\"text-decoration: none !important;font-size: 14px !important;font-weight:bold !important;white-space:nowrap;font-family:Ember,'Amazon Ember',Arial,sans-serif; color: #0F1111;\"><strong>Buy Again</strong></a></td></tr></table></td></tr></table><!--[if mso]></td></tr></table></td></tr><![endif]--> <!--[if mso | IE]></table><![endif]--></td></tr></tbody></table></div><!--[if mso | IE]></td></tr></table><![endif]--> <!--[if mso | IE]><table align=\"center\" border=\"0\" cellpadding=\"0\" cellspacing=\"0\" class=\"rootContent-outlook moduleId-heroImage-outlook\" role=\"presentation\" style=\"width:600px;\" width=\"600\" bgcolor=\"#ffffff\" ><tr><td style=\"line-height:0px;font-size:0px;mso-line-height-rule:exactly;\"><![endif]--><div class=\"rootContent moduleId-heroImage\" style=\"background:#ffffff;background-color:#ffffff;margin:0px auto;max-width:600px;\"><table align=\"center\" border=\"0\" cellpadding=\"0\" cellspacing=\"0\" role=\"presentation\" style=\"background:#ffffff;background-color:#ffffff;width:100%;\"><tbody><tr><td style=\"direction:ltr;font-size:0px;padding:0px 0px 4px 0px;text-align:left;\"><!--[if mso | IE]><table role=\"presentation\" border=\"0\" cellpadding=\"0\" cellspacing=\"0\"><![endif]--> <!--[if mso | IE]><tr><td align=\"left\" class=\"sonar-hero-image-outlook sonar-hero-image-v1-outlook\" width=\"600px\" ><![endif]-->        <a href=\"https://www.amazon.com/gp/r.html?C=3BEF3T114MSHJ&K=PLA15W5PCRNT&M=urn:rtn:msg:202603240111072e6e5e7d64a94aec9e4b685effc0p0na&R=1VX4UMTQIQB9R&T=C&U=https%3A%2F%2Fwww.amazon.com%2Fdeals%3Fref_%3Dpe_101622500_1365358730_HI_01_01_IMG_01&H=WAXLAKML5DEM4GOOEXILLTROTOOA&ref_=pe_101622500_1365358730_HI_01_01_IMG_01\" target=\"_blank\"> <img width=\"600\" src=\"https://m.media-amazon.com/images/G/01/Outbound/2026/EvergreenEmails/Deals/March/3.16-Deals/AME_Evergreen_Deals_0316_Email_Hero_1800x384.gif\" alt=\"Today's Deals\" style=\"width:100%;max-width:600px;display:block;border-radius:0px;\"> </a><!--[if mso | IE]></td></tr><![endif]--> <!--[if mso | IE]></table><![endif]--></a></td></tr></tbody></table></div><!--[if mso | IE]></td></tr></table><![endif]--> <!--[if mso | IE]><table align=\"center\" border=\"0\" cellpadding=\"0\" cellspacing=\"0\" class=\"rootContent-outlook moduleId-asinGridHve-outlook\" role=\"presentation\" style=\"width:600px;\" width=\"600\" bgcolor=\"#ffffff\" ><tr><td style=\"line-height:0px;font-size:0px;mso-line-height-rule:exactly;\"><![endif]--><div class=\"rootContent moduleId-asinGridHve\" style=\"background:#ffffff;background-color:#ffffff;margin:0px auto;max-width:600px;\"><table align=\"center\" border=\"0\" cellpadding=\"0\" cellspacing=\"0\" role=\"presentation\" style=\"background:#ffffff;background-color:#ffffff;width:100%;\"><tbody><tr><td style=\"direction:ltr;font-size:0px;padding:4px 8px 4px 8px;text-align:left;\"><!--[if mso | IE]><table role=\"presentation\" border=\"0\" cellpadding=\"0\" cellspacing=\"0\"><![endif]--><!--[if mso | IE]><tr><td align=\"left\" class=\"sonar-asin-grid-hve-outlook sonar-asin-grid-hve-v1-outlook\" width=\"600px\" ><table align=\"center\" border=\"0\" cellpadding=\"0\" cellspacing=\"0\" class=\"rio-card-outlook\" role=\"presentation\" style=\"width:584px;\" width=\"584\" bgcolor=\"#ffffff\" ><tr><td style=\"line-height:0px;font-size:0px;mso-line-height-rule:exactly;\"><![endif]--><div class=\"rio-card\" style=\"background:#ffffff;background-color:#ffffff;margin:0px auto;border-radius:4px;max-width:584px;\"><table align=\"center\" border=\"0\" cellpadding=\"0\" cellspacing=\"0\" role=\"presentation\" style=\"background:#ffffff;background-color:#ffffff;width:100%;border-radius:4px;\"><tbody><tr><td style=\"direction:ltr;font-size:0px;padding:4px 8px 4px 8px;text-align:left;\"><!--[if mso | IE]><table role=\"presentation\" border=\"0\" cellpadding=\"0\" cellspacing=\"0\"><tr><td align=\"left\" class=\"\" width=\"584px\" ><![endif]-->  <table cellpadding=\"0\" cellspacing=\"0\" role=\"presentation\" width=\"100%\" border=\"0\" style=\"color:#000000;font-family:Ember,'Amazon Ember',Arial,sans-serif;font-size:15px;line-height:22px;table-layout:auto;width:100%;border:none;\"><tr><td width=\"65%\"><div style=\"font-family:Ember,'Amazon Ember',Arial,sans-serif;font-size:15px;line-height:1;text-align:left;color:#000000;\"><h2 style=\"margin:0;padding:0;font-family:Ember,'Amazon Ember',Arial,sans-serif;font-weight:700;font-size:18px;line-height:22px;color:#0F1111;\" class=\"rio-header rio-header-590\">Deals for you</h2></div></td><td width=\"35%\" align=\"right\">  <div style=\"font-family:Ember,'Amazon Ember',Arial,sans-serif;font-size:15px;font-weight:400;line-height:21px;text-align:right;color:#0F1111;\"><span class=\"rio-text rio-text-897\"><a href=\"https://www.amazon.com/gp/r.html?C=3BEF3T114MSHJ&K=PLA15W5PCRNT&M=urn:rtn:msg:202603240111072e6e5e7d64a94aec9e4b685effc0p0na&R=VQL66X2719F8&T=C&U=https%3A%2F%2Fwww.amazon.com%2Fdeals%3Fbubble-id%3Ddiscounts-collection-for-you%26ref_%3Dpe_101622500_1365358730_AGH_02_01_BT_02&H=F6C2VG9AAPBA0MFAKUMJQBLZQQUA&ref_=pe_101622500_1365358730_AGH_02_01_BT_02\" style=\"text-decoration: underline !important;color:#0F1111;\" target=\"_blank\">Shop now</a></span></div></td></tr></table><div aria-hidden=\"true\" style=\"height:8px;line-height:8px\">&nbsp;</div><!--[if mso | IE]></td></tr><![endif]--> <!--[if mso | IE]><tr><td align=\"left\" class=\"asin-grid-custom-border-outlook\" width=\"584px\" ><table align=\"center\" border=\"0\" cellpadding=\"0\" cellspacing=\"0\" class=\"asin-grid-custom-border-outlook\" role=\"presentation\" style=\"width:568px;\" width=\"568\" ><tr><td style=\"line-height:0px;font-size:0px;mso-line-height-rule:exactly;\"><![endif]--><div class=\"asin-grid-custom-border\" style=\"margin:0px auto;max-width:568px;\"><table align=\"center\" border=\"0\" cellpadding=\"0\" cellspacing=\"0\" role=\"presentation\" style=\"width:100%;\"><tbody><tr><td style=\"direction:ltr;font-size:0px;padding:0;text-align:left;\"><!--[if mso | IE]><table role=\"presentation\" border=\"0\" cellpadding=\"0\" cellspacing=\"0\"><tr><td align=\"left\" class=\"\" width=\"568px\" ><![endif]--> <table class=\"rio-table-grid-table\" role=\"list\" width=\"100%\" border=\"0\" style=\"width:100%;font-size:0;line-height:0;mso-line-height-rule:exactly;\"><tr><td class=\"rio-table-grid-td-bg\" role=\"listitem\" valign=\"top\" width=\"49%\" style=\"width:49%;  border-radius:8px; background-color: #f7f7f7 \">    <table role=\"presentation\" style=\"table-layout:fixed;width:100%;max-width:100%;background-color:#f7f7f7;border-radius:8px;\" class=\"asin-container\"><tr><td style=\"padding:0px;\"><table role=\"presentation\" class=\"rio-asin-container-image\" width=\"100%\"><tr><td align=\"center\"><a href=\"https://www.amazon.com/gp/r.html?C=3BEF3T114MSHJ&K=PLA15W5PCRNT&M=urn:rtn:msg:202603240111072e6e5e7d64a94aec9e4b685effc0p0na&R=1OIENWGFJU4AS&T=C&U=https%3A%2F%2Fwww.amazon.com%2Fdp%2FB0CLNRBR5Y%2F%3Fref_%3Dpe_101622500_1365358730_AGH_02_00_IMG_02_pd_ot_dealz_dotd_2p_0_l%26%26pd_rd_wg%3D45Wxi%26pd_rd_w%3DU0Q8x%26pf_rd_p%3D145211a5-a5d7-4fe6-8f8f-9db01f9b61c0%26pd_rd_r%3Dca7be7ae-69bf-4005-96fb-f05b7e1f6a82%26content-id%3Damzn1.sym.145211a5-a5d7-4fe6-8f8f-9db01f9b61c0&H=OTMQUTP8V3CBUSALKG8KZUW1KTEA&ref_=pe_101622500_1365358730_AGH_02_00_IMG_02_pd_ot_dealz_dotd_2p_0_l\" target=\"_blank\"><img src=\"https://m.media-amazon.com/images/I/5129dSLDQLL._SR538,538_.jpg\" alt=\"JSAUX Displayport Cable\" align=\"center\" width=\"269\" height=\"269\" style=\"width: 100%;height: auto;max-width:269px;max-height:269px;\"></a></td></tr></table><div style=\"padding:4px;\">    <mj-raw></mj-raw><table width=\"100%\" style=\"width: 100%;\" role=\"presentation\"><tbody><tr><td style='text-align: left; direction=\"ltr\" !important;'><table style=\"border-spacing: 20px;\" role=\"presentation\"><tr style=\"display: block; padding-bottom: 2px\"><td style=\"text-align: left;\"><span class=\"priceBadge\" style=\"font-weight:700;font-size:11px;line-height:12px;display:block;color:#CC0C39;\">      Limited time deal  </span></td></tr><tr style=\"display: block; padding-bottom: 2px\"><td style=\"text-align: left; height: 24px; padding-right: 6px;\"><span class=\"priceDiscount\" style=\"font-weight:400;font-size:11px;line-height:16px;color:#FFFFFF;background-color:#CC0C39;padding:4px 6px 4px 6px;white-space:nowrap;border-radius:2px;\">-10% </span></td></tr> </table></td></tr></tbody></table><mj-raw></mj-raw></div></td></tr></table></td><td aria-hidden=\"true\" width=\"2%\" style=\"width:2%;\"><div style=\"width:8px\">&nbsp;</div></td>  <td class=\"rio-table-grid-td-bg\" role=\"listitem\" valign=\"top\" width=\"49%\" style=\"width:49%;  border-radius:8px; background-color: #f7f7f7 \">    <table role=\"presentation\" style=\"table-layout:fixed;width:100%;max-width:100%;background-color:#f7f7f7;border-radius:8px;\" class=\"asin-container\"><tr><td style=\"padding:0px;\"><table role=\"presentation\" class=\"rio-asin-container-image\" width=\"100%\"><tr><td align=\"center\"><a href=\"https://www.amazon.com/gp/r.html?C=3BEF3T114MSHJ&K=PLA15W5PCRNT&M=urn:rtn:msg:202603240111072e6e5e7d64a94aec9e4b685effc0p0na&R=109GPBWAQFK3S&T=C&U=https%3A%2F%2Fwww.amazon.com%2Fdp%2FB07T5SY43L%2F%3Fref_%3Dpe_101622500_1365358730_AGH_02_01_IMG_02_pd_ot_dealz_dotd_2p_1_l%26%26pd_rd_wg%3D45Wxi%26pd_rd_w%3DU0Q8x%26pf_rd_p%3D145211a5-a5d7-4fe6-8f8f-9db01f9b61c0%26pd_rd_r%3Dca7be7ae-69bf-4005-96fb-f05b7e1f6a82%26content-id%3Damzn1.sym.145211a5-a5d7-4fe6-8f8f-9db01f9b61c0&H=REHTXZ1Z7RMYGZQLI2FHGAEL9ZMA&ref_=pe_101622500_1365358730_AGH_02_01_IMG_02_pd_ot_dealz_dotd_2p_1_l\" target=\"_blank\"><img src=\"https://m.media-amazon.com/images/I/41Mr-S3C6XL._SR538,538_.jpg\" alt=\"HUANUO Monitor Stand\" align=\"center\" width=\"269\" height=\"269\" style=\"width: 100%;height: auto;max-width:269px;max-height:269px;\"></a></td></tr></table><div style=\"padding:4px;\">    <mj-raw></mj-raw><table width=\"100%\" style=\"width: 100%;\" role=\"presentation\"><tbody><tr><td style='text-align: left; direction=\"ltr\" !important;'><table style=\"border-spacing: 20px;\" role=\"presentation\"><tr style=\"display: block; padding-bottom: 2px\"><td style=\"text-align: left;\"><span class=\"priceBadge\" style=\"font-weight:700;font-size:11px;line-height:12px;display:block;color:#CC0C39;\">      Limited time deal  </span></td></tr><tr style=\"display: block; padding-bottom: 2px\"><td style=\"text-align: left; height: 24px; padding-right: 6px;\"><span class=\"priceDiscount\" style=\"font-weight:400;font-size:11px;line-height:16px;color:#FFFFFF;background-color:#CC0C39;padding:4px 6px 4px 6px;white-space:nowrap;border-radius:2px;\">-21% </span></td></tr> </table></td></tr></tbody></table><mj-raw></mj-raw></div></td></tr></table></td></tr><tr aria-hidden=\"true\"><td colspan=\"3\" width=\"100%\" height=\"8\" style=\"width:100%; height:8px; line-height:8px; mso-line-height-rule:exactly;\">&nbsp;</td></tr><tr>  <td class=\"rio-table-grid-td-bg\" role=\"listitem\" valign=\"top\" width=\"49%\" style=\"width:49%;  border-radius:8px; background-color: #f7f7f7 \">    <table role=\"presentation\" style=\"table-layout:fixed;width:100%;max-width:100%;background-color:#f7f7f7;border-radius:8px;\" class=\"asin-container\"><tr><td style=\"padding:0px;\"><table role=\"presentation\" class=\"rio-asin-container-image\" width=\"100%\"><tr><td align=\"center\"><a href=\"https://www.amazon.com/gp/r.html?C=3BEF3T114MSHJ&K=PLA15W5PCRNT&M=urn:rtn:msg:202603240111072e6e5e7d64a94aec9e4b685effc0p0na&R=GITTTN8LRRL4&T=C&U=https%3A%2F%2Fwww.amazon.com%2Fdp%2FB0CN7X7JQS%2F%3Fref_%3Dpe_101622500_1365358730_AGH_02_02_IMG_02_pd_ot_dealz_dotd_2p_2_l%26%26pd_rd_wg%3D45Wxi%26pd_rd_w%3DU0Q8x%26pf_rd_p%3D145211a5-a5d7-4fe6-8f8f-9db01f9b61c0%26pd_rd_r%3Dca7be7ae-69bf-4005-96fb-f05b7e1f6a82%26content-id%3Damzn1.sym.145211a5-a5d7-4fe6-8f8f-9db01f9b61c0&H=L4ZJG8JSBTVQP8I3PT6XIQSAWPYA&ref_=pe_101622500_1365358730_AGH_02_02_IMG_02_pd_ot_dealz_dotd_2p_2_l\" target=\"_blank\"><img src=\"https://m.media-amazon.com/images/I/31nFvknDDvL._SR538,538_.jpg\" alt=\"Carhartt T-Shirt\" align=\"center\" width=\"269\" height=\"269\" style=\"width: 100%;height: auto;max-width:269px;max-height:269px;\"></a></td></tr></table><div style=\"padding:4px;\">    <mj-raw></mj-raw><table width=\"100%\" style=\"width: 100%;\" role=\"presentation\"><tbody><tr><td style='text-align: left; direction=\"ltr\" !important;'><table style=\"border-spacing: 20px;\" role=\"presentation\"><tr style=\"display: block; padding-bottom: 2px\"><td style=\"text-align: left;\"><span class=\"priceBadge\" style=\"font-weight:700;font-size:11px;line-height:12px;display:block;color:#CC0C39;\">      Limited time deal  </span></td></tr><tr style=\"display: block; padding-bottom: 2px\"><td style=\"text-align: left; height: 24px; padding-right: 6px;\"><span class=\"priceDiscount\" style=\"font-weight:400;font-size:11px;line-height:16px;color:#FFFFFF;background-color:#CC0C39;padding:4px 6px 4px 6px;white-space:nowrap;border-radius:2px;\">-33% </span></td></tr> </table></td></tr></tbody></table><mj-raw></mj-raw></div></td></tr></table></td><td aria-hidden=\"true\" width=\"2%\" style=\"width:2%;\"><div style=\"width:8px\">&nbsp;</div></td>  <td class=\"rio-table-grid-td-bg\" role=\"listitem\" valign=\"top\" width=\"49%\" style=\"width:49%;  border-radius:8px; background-color: #f7f7f7 \">    <table role=\"presentation\" style=\"table-layout:fixed;width:100%;max-width:100%;background-color:#f7f7f7;border-radius:8px;\" class=\"asin-container\"><tr><td style=\"padding:0px;\"><table role=\"presentation\" class=\"rio-asin-container-image\" width=\"100%\"><tr><td align=\"center\"><a href=\"https://www.amazon.com/gp/r.html?C=3BEF3T114MSHJ&K=PLA15W5PCRNT&M=urn:rtn:msg:202603240111072e6e5e7d64a94aec9e4b685effc0p0na&R=3JJOR1YCR6UV7&T=C&U=https%3A%2F%2Fwww.amazon.com%2Fdp%2FB0F9WKBFQR%2F%3Fref_%3Dpe_101622500_1365358730_AGH_02_03_IMG_02_pd_ot_dealz_dotd_2p_3_l%26%26pd_rd_wg%3D45Wxi%26pd_rd_w%3DU0Q8x%26pf_rd_p%3D145211a5-a5d7-4fe6-8f8f-9db01f9b61c0%26pd_rd_r%3Dca7be7ae-69bf-4005-96fb-f05b7e1f6a82%26content-id%3Damzn1.sym.145211a5-a5d7-4fe6-8f8f-9db01f9b61c0&H=XCKGD16IMHQBOOTY8MPQ2AOXWBSA&ref_=pe_101622500_1365358730_AGH_02_03_IMG_02_pd_ot_dealz_dotd_2p_3_l\" target=\"_blank\"><img src=\"https://m.media-amazon.com/images/I/41-Is680+FL._SR538,538_.jpg\" alt=\"AOOSTAR Mini PC\" align=\"center\" width=\"269\" height=\"269\" style=\"width: 100%;height: auto;max-width:269px;max-height:269px;\"></a></td></tr></table><div style=\"padding:4px;\">    <mj-raw></mj-raw><table width=\"100%\" style=\"width: 100%;\" role=\"presentation\"><tbody><tr><td style='text-align: left; direction=\"ltr\" !important;'><table style=\"border-spacing: 20px;\" role=\"presentation\"><tr style=\"display: block; padding-bottom: 2px\"><td style=\"text-align: left;\"><span class=\"priceBadge\" style=\"font-weight:700;font-size:11px;line-height:12px;display:block;color:#CC0C39;\">      Limited time deal  </span></td></tr><tr style=\"display: block; padding-bottom: 2px\"><td style=\"text-align: left; height: 24px; padding-right: 6px;\"><span class=\"priceDiscount\" style=\"font-weight:400;font-size:11px;line-height:16px;color:#FFFFFF;background-color:#CC0C39;padding:4px 6px 4px 6px;white-space:nowrap;border-radius:2px;\">-15% </span></td></tr> </table></td></tr></tbody></table><mj-raw></mj-raw></div></td></tr></table></td>   </tr></table><!--[if mso | IE]></td></tr></table><![endif]--></td></tr></tbody></table></div><!--[if mso | IE]></td></tr></table></td></tr></table><![endif]--></td></tr></tbody></table></div><!--[if mso | IE]></td></tr></table></td></tr><![endif]-->   <!--[if mso | IE]></table><![endif]--></td></tr></tbody></table></div><!--[if mso | IE]></td></tr></table><![endif]--> <!--[if mso | IE]><table align=\"center\" border=\"0\" cellpadding=\"0\" cellspacing=\"0\" class=\"rootContent-outlook moduleId-bannerImage-outlook\" role=\"presentation\" style=\"width:600px;\" width=\"600\" bgcolor=\"#ffffff\" ><tr><td style=\"line-height:0px;font-size:0px;mso-line-height-rule:exactly;\"><![endif]--><div class=\"rootContent moduleId-bannerImage\" style=\"background:#ffffff;background-color:#ffffff;margin:0px auto;max-width:600px;\"><table align=\"center\" border=\"0\" cellpadding=\"0\" cellspacing=\"0\" role=\"presentation\" style=\"background:#ffffff;background-color:#ffffff;width:100%;\"><tbody><tr><td style=\"direction:ltr;font-size:0px;padding:4px 8px 4px 8px;text-align:left;\"><!--[if mso | IE]><table role=\"presentation\" border=\"0\" cellpadding=\"0\" cellspacing=\"0\"><![endif]--> <!--[if mso | IE]><tr><td align=\"left\" class=\"sonar-banner-image-outlook sonar-banner-image-v1-outlook\" width=\"600px\" ><table align=\"center\" border=\"0\" cellpadding=\"0\" cellspacing=\"0\" class=\"rio-card-outlook\" role=\"presentation\" style=\"width:584px;\" width=\"584\" bgcolor=\"#ffffff\" ><tr><td style=\"line-height:0px;font-size:0px;mso-line-height-rule:exactly;\"><![endif]--><div class=\"rio-card\" style=\"background:#ffffff;background-color:#ffffff;margin:0px auto;border-radius:4px;max-width:584px;\"><table align=\"center\" border=\"0\" cellpadding=\"0\" cellspacing=\"0\" role=\"presentation\" style=\"background:#ffffff;background-color:#ffffff;width:100%;border-radius:4px;\"><tbody><tr><td style=\"direction:ltr;font-size:0px;padding:4px 8px 4px 8px;text-align:left;\"><!--[if mso | IE]><table role=\"presentation\" border=\"0\" cellpadding=\"0\" cellspacing=\"0\"><![endif]-->  <!--[if mso | IE]><tr><td align=\"left\" class=\"\" width=\"584px\" ><![endif]-->        <a href=\"https://www.amazon.com/gp/r.html?C=3BEF3T114MSHJ&K=PLA15W5PCRNT&M=urn:rtn:msg:202603240111072e6e5e7d64a94aec9e4b685effc0p0na&R=2DVIJMGH8EEFG&T=C&U=https%3A%2F%2Fwww.amazon.com%2Fevents%2Fbigspringsale%3Fref_%3Dpe_101622500_1365358730_BI_03_01_IMG_03&H=UCAKXR06U4DJRRXKIQHQSKFFJXOA&ref_=pe_101622500_1365358730_BI_03_01_IMG_03\" target=\"_blank\"> <img width=\"568\" src=\"https://m.media-amazon.com/images/G/01/Outbound/2026/EvergreenEmails/Deals/March/3.23-Deals/AME_Evergreen_Deals_3-23_Email_02_Banner_BSS_1704x417.gif\" alt=\"Big Spring Sale starts March 25. Shop early deals now\" style=\"width:100%;max-width:568px;display:block;border-radius:4px;\"> </a><!--[if mso | IE]></td></tr><![endif]-->  <!--[if mso | IE]></table><![endif]--></a></td></tr></tbody></table></div><!--[if mso | IE]></td></tr></table></td></tr><![endif]-->  <!--[if mso | IE]></table><![endif]--></td></tr></tbody></table></div><!--[if mso | IE]></td></tr></table><![endif]--> <!--[if mso | IE]><table align=\"center\" border=\"0\" cellpadding=\"0\" cellspacing=\"0\" class=\"rootContent-outlook moduleId-categoryGrid2by2-outlook\" role=\"presentation\" style=\"width:600px;\" width=\"600\" bgcolor=\"#ffffff\" ><tr><td style=\"line-height:0px;font-size:0px;mso-line-height-rule:exactly;\"><![endif]--><div class=\"rootContent moduleId-categoryGrid2by2\" style=\"background:#ffffff;background-color:#ffffff;margin:0px auto;max-width:600px;\"><table align=\"center\" border=\"0\" cellpadding=\"0\" cellspacing=\"0\" role=\"presentation\" style=\"background:#ffffff;background-color:#ffffff;width:100%;\"><tbody><tr><td style=\"direction:ltr;font-size:0px;padding:4px 8px 4px 8px;text-align:left;\"><!--[if mso | IE]><table role=\"presentation\" border=\"0\" cellpadding=\"0\" cellspacing=\"0\"><![endif]-->     <!--[if mso | IE]><tr><td align=\"left\" class=\"sonar-category-grid-hve-outlook sonar-category-grid-hve-v1-outlook\" width=\"600px\" ><table align=\"center\" border=\"0\" cellpadding=\"0\" cellspacing=\"0\" class=\"rio-card-outlook\" role=\"presentation\" style=\"width:584px;\" width=\"584\" bgcolor=\"#ffffff\" ><tr><td style=\"line-height:0px;font-size:0px;mso-line-height-rule:exactly;\"><![endif]--><div class=\"rio-card\" style=\"background:#ffffff;background-color:#ffffff;margin:0px auto;border-radius:4px;max-width:584px;\"><table align=\"center\" border=\"0\" cellpadding=\"0\" cellspacing=\"0\" role=\"presentation\" style=\"background:#ffffff;background-color:#ffffff;width:100%;border-radius:4px;\"><tbody><tr><td style=\"direction:ltr;font-size:0px;padding:4px 8px 4px 8px;text-align:left;\"><!--[if mso | IE]><table role=\"presentation\" border=\"0\" cellpadding=\"0\" cellspacing=\"0\"><tr><td align=\"left\" class=\"\" width=\"584px\" ><![endif]-->  <table cellpadding=\"0\" cellspacing=\"0\" role=\"presentation\" width=\"100%\" border=\"0\" style=\"color:#000000;font-family:Ember,'Amazon Ember',Arial,sans-serif;font-size:15px;line-height:22px;table-layout:auto;width:100%;border:none;\"><tr><td width=\"65%\"><div style=\"font-family:Ember,'Amazon Ember',Arial,sans-serif;font-size:15px;line-height:1;text-align:left;color:#000000;\"><h2 style=\"margin:0;padding:0;font-family:Ember,'Amazon Ember',Arial,sans-serif;font-weight:700;font-size:18px;line-height:22px;color:#0F1111;\" class=\"rio-header rio-header-592\">Explore deals by category</h2></div></td><td width=\"35%\" align=\"right\">  <div style=\"font-family:Ember,'Amazon Ember',Arial,sans-serif;font-size:15px;font-weight:400;line-height:21px;text-align:right;color:#0F1111;\"><span class=\"rio-text rio-text-902\"><a href=\"https://www.amazon.com/gp/r.html?C=3BEF3T114MSHJ&K=PLA15W5PCRNT&M=urn:rtn:msg:202603240111072e6e5e7d64a94aec9e4b685effc0p0na&R=2C1UYFIPGIQP4&T=C&U=https%3A%2F%2Fwww.amazon.com%2Fdeals%3Fref_%3Dpe_101622500_1365358730_CGH_04_01_BT_04&H=MF7JNJPNZ63GEZXGZMH5G3SZOT0A&ref_=pe_101622500_1365358730_CGH_04_01_BT_04\" style=\"text-decoration: underline !important;color:#0F1111;\" target=\"_blank\">Shop all</a></span></div></td></tr></table><div aria-hidden=\"true\" style=\"height:8px;line-height:8px\">&nbsp;</div><!--[if mso | IE]></td></tr><tr><td align=\"left\" class=\"\" width=\"584px\" ><![endif]--> <table class=\"rio-table-grid-table\" role=\"list\" width=\"100%\" border=\"0\" style=\"width:100%;font-size:0;line-height:0;mso-line-height-rule:exactly;\"><tr>  <td class=\"\" role=\"listitem\" valign=\"top\" width=\"49%\" style=\"width:49%; \">     <a href=\"https://www.amazon.com/gp/r.html?C=3BEF3T114MSHJ&K=PLA15W5PCRNT&M=urn:rtn:msg:202603240111072e6e5e7d64a94aec9e4b685effc0p0na&R=3SQ2UHVY2K8DC&T=C&U=https%3A%2F%2Fwww.amazon.com%2Fdeals%3Fbubble-id%3Dkitchen%26ref_%3Dpe_101622500_1365358730_CGH_04_00_IMG_04&H=5ZBTWS9WAFWRX5PDHAAUF0R1C7AA&ref_=pe_101622500_1365358730_CGH_04_00_IMG_04\" target=\"_blank\"> <img width=\"276\" src=\"https://m.media-amazon.com/images/G/01/Outbound/2026/EvergreenEmails/Deals/February/2.23-Deals/AME_Evergreen_Deals_2-23_Email__04A_CatQuad_kitchen_840x630.png\" alt=\"Kitchen\" align=\"center\" style=\"width:100%;max-width:276px;display:block;border-radius:8px;\"> </a>   <div aria-hidden=\"true\" style=\"height:4px;line-height:4px\">&nbsp;</div><div style=\"font-family:Ember,'Amazon Ember',Arial,sans-serif;font-size:15px;font-weight:400;line-height:20px;text-align:left;color:#0F1111;\"><span class=\"rio-text rio-text-904\" aria-hidden=\"true\">Kitchen</span></div> </td><td aria-hidden=\"true\" width=\"2%\" style=\"width:2%;\"><div style=\"width:8px\">&nbsp;</div></td>    <td class=\"\" role=\"listitem\" valign=\"top\" width=\"49%\" style=\"width:49%; \">     <a href=\"https://www.amazon.com/gp/r.html?C=3BEF3T114MSHJ&K=PLA15W5PCRNT&M=urn:rtn:msg:202603240111072e6e5e7d64a94aec9e4b685effc0p0na&R=FG9HITWQSZAE&T=C&U=https%3A%2F%2Fwww.amazon.com%2Fdeals%3Fbubble-id%3Dfashion%26ref_%3Dpe_101622500_1365358730_CGH_04_01_IMG_04&H=S4PZVTTA7JQBJDT0KCXPTAQVVDIA&ref_=pe_101622500_1365358730_CGH_04_01_IMG_04\" target=\"_blank\"> <img width=\"276\" src=\"https://m.media-amazon.com/images/G/01/Outbound/2026/EvergreenEmails/Deals/February/2.23-Deals/AME_Evergreen_Deals_2-9_Email_04B_CatQuad_fashion_840x630.png\" alt=\"Fashion\" align=\"center\" style=\"width:100%;max-width:276px;display:block;border-radius:8px;\"> </a>   <div aria-hidden=\"true\" style=\"height:4px;line-height:4px\">&nbsp;</div><div style=\"font-family:Ember,'Amazon Ember',Arial,sans-serif;font-size:15px;font-weight:400;line-height:20px;text-align:left;color:#0F1111;\"><span class=\"rio-text rio-text-904\" aria-hidden=\"true\">Fashion</span></div> </td></tr><tr aria-hidden=\"true\"><td colspan=\"3\" width=\"100%\" height=\"8\" style=\"width:100%; height:8px; line-height:8px; mso-line-height-rule:exactly;\">&nbsp;</td></tr><tr>    <td class=\"\" role=\"listitem\" valign=\"top\" width=\"49%\" style=\"width:49%; \">     <a href=\"https://www.amazon.com/gp/r.html?C=3BEF3T114MSHJ&K=PLA15W5PCRNT&M=urn:rtn:msg:202603240111072e6e5e7d64a94aec9e4b685effc0p0na&R=2R89GTJW4B0JF&T=C&U=https%3A%2F%2Fwww.amazon.com%2Fdeals%3Fbubble-id%3Dsport-outdoors%26ref_%3Dpe_101622500_1365358730_CGH_04_02_IMG_04&H=OYVSBF3CMBT4TK58WM18FRYYOEWA&ref_=pe_101622500_1365358730_CGH_04_02_IMG_04\" target=\"_blank\"> <img width=\"276\" src=\"https://m.media-amazon.com/images/G/01/Outbound/2026/EvergreenEmails/Deals/February/2.23-Deals/AME_Evergreen_Deals_2-9_Email_04C_CatQuad_sports_840x630.png\" alt=\"Sports &amp; outdoors\" align=\"center\" style=\"width:100%;max-width:276px;display:block;border-radius:8px;\"> </a>   <div aria-hidden=\"true\" style=\"height:4px;line-height:4px\">&nbsp;</div><div style=\"font-family:Ember,'Amazon Ember',Arial,sans-serif;font-size:15px;font-weight:400;line-height:20px;text-align:left;color:#0F1111;\"><span class=\"rio-text rio-text-904\" aria-hidden=\"true\">Sports &amp; outdoors</span></div> </td><td aria-hidden=\"true\" width=\"2%\" style=\"width:2%;\"><div style=\"width:8px\">&nbsp;</div></td>    <td class=\"\" role=\"listitem\" valign=\"top\" width=\"49%\" style=\"width:49%; \">     <a href=\"https://www.amazon.com/gp/r.html?C=3BEF3T114MSHJ&K=PLA15W5PCRNT&M=urn:rtn:msg:202603240111072e6e5e7d64a94aec9e4b685effc0p0na&R=14W7QZ1QF3CN9&T=C&U=https%3A%2F%2Fwww.amazon.com%2Fdeals%3Fbubble-id%3Dhome%26ref_%3Dpe_101622500_1365358730_CGH_04_03_IMG_04&H=QALHCIDEJVBG63AZQIYOO868YH8A&ref_=pe_101622500_1365358730_CGH_04_03_IMG_04\" target=\"_blank\"> <img width=\"276\" src=\"https://m.media-amazon.com/images/G/01/Outbound/2026/EvergreenEmails/Deals/February/2.23-Deals/AME_Evergreen_Deals_2-9_Email_04D_CatQuad_home_840x630.png\" alt=\"Home\" align=\"center\" style=\"width:100%;max-width:276px;display:block;border-radius:8px;\"> </a>   <div aria-hidden=\"true\" style=\"height:4px;line-height:4px\">&nbsp;</div><div style=\"font-family:Ember,'Amazon Ember',Arial,sans-serif;font-size:15px;font-weight:400;line-height:20px;text-align:left;color:#0F1111;\"><span class=\"rio-text rio-text-904\" aria-hidden=\"true\">Home</span></div> </td>    </tr></table><!--[if mso | IE]></td></tr></table><![endif]--></td></tr></tbody></table></div><!--[if mso | IE]></td></tr></table></td></tr><![endif]--> <!--[if mso | IE]></table><![endif]--></td></tr></tbody></table></div><!--[if mso | IE]></td></tr></table><![endif]--> <!--[if mso | IE]><table align=\"center\" border=\"0\" cellpadding=\"0\" cellspacing=\"0\" class=\"rootContent-outlook moduleId-asinGridHve-outlook\" role=\"presentation\" style=\"width:600px;\" width=\"600\" bgcolor=\"#ffffff\" ><tr><td style=\"line-height:0px;font-size:0px;mso-line-height-rule:exactly;\"><![endif]--><div class=\"rootContent moduleId-asinGridHve\" style=\"background:#ffffff;background-color:#ffffff;margin:0px auto;max-width:600px;\"><table align=\"center\" border=\"0\" cellpadding=\"0\" cellspacing=\"0\" role=\"presentation\" style=\"background:#ffffff;background-color:#ffffff;width:100%;\"><tbody><tr><td style=\"direction:ltr;font-size:0px;padding:4px 8px 4px 8px;text-align:left;\"><!--[if mso | IE]><table role=\"presentation\" border=\"0\" cellpadding=\"0\" cellspacing=\"0\"><![endif]--><!--[if mso | IE]><tr><td align=\"left\" class=\"sonar-asin-grid-hve-outlook sonar-asin-grid-hve-v1-outlook\" width=\"600px\" ><table align=\"center\" border=\"0\" cellpadding=\"0\" cellspacing=\"0\" class=\"rio-card-outlook\" role=\"presentation\" style=\"width:584px;\" width=\"584\" bgcolor=\"#ffffff\" ><tr><td style=\"line-height:0px;font-size:0px;mso-line-height-rule:exactly;\"><![endif]--><div class=\"rio-card\" style=\"background:#ffffff;background-color:#ffffff;margin:0px auto;border-radius:4px;max-width:584px;\"><table align=\"center\" border=\"0\" cellpadding=\"0\" cellspacing=\"0\" role=\"presentation\" style=\"background:#ffffff;background-color:#ffffff;width:100%;border-radius:4px;\"><tbody><tr><td style=\"direction:ltr;font-size:0px;padding:4px 8px 4px 8px;text-align:left;\"><!--[if mso | IE]><table role=\"presentation\" border=\"0\" cellpadding=\"0\" cellspacing=\"0\"><tr><td align=\"left\" class=\"\" width=\"584px\" ><![endif]-->  <table cellpadding=\"0\" cellspacing=\"0\" role=\"presentation\" width=\"100%\" border=\"0\" style=\"color:#000000;font-family:Ember,'Amazon Ember',Arial,sans-serif;font-size:15px;line-height:22px;table-layout:auto;width:100%;border:none;\"><tr><td width=\"65%\"><div style=\"font-family:Ember,'Amazon Ember',Arial,sans-serif;font-size:15px;line-height:1;text-align:left;color:#000000;\"><h2 style=\"margin:0;padding:0;font-family:Ember,'Amazon Ember',Arial,sans-serif;font-weight:700;font-size:18px;line-height:22px;color:#0F1111;\" class=\"rio-header rio-header-593\">Most-loved deals for you</h2></div></td><td width=\"35%\" align=\"right\">  <div style=\"font-family:Ember,'Amazon Ember',Arial,sans-serif;font-size:15px;font-weight:400;line-height:21px;text-align:right;color:#0F1111;\"><span class=\"rio-text rio-text-905\"><a href=\"https://www.amazon.com/gp/r.html?C=3BEF3T114MSHJ&K=PLA15W5PCRNT&M=urn:rtn:msg:202603240111072e6e5e7d64a94aec9e4b685effc0p0na&R=2AX6MMR4MU6HC&T=C&U=https%3A%2F%2Fwww.amazon.com%2Fdeals%3Fbubble-id%3Ddeals-collection-cml%26ref_%3Dpe_101622500_1365358730_AGH_05_01_BT_05&H=ZIAUVWAJEABDXA2S8KZQXEZWFLKA&ref_=pe_101622500_1365358730_AGH_05_01_BT_05\" style=\"text-decoration: underline !important;color:#0F1111;\" target=\"_blank\">Shop now</a></span></div></td></tr></table><div aria-hidden=\"true\" style=\"height:8px;line-height:8px\">&nbsp;</div><!--[if mso | IE]></td></tr><![endif]--> <!--[if mso | IE]><tr><td align=\"left\" class=\"asin-grid-custom-border-outlook\" width=\"584px\" ><table align=\"center\" border=\"0\" cellpadding=\"0\" cellspacing=\"0\" class=\"asin-grid-custom-border-outlook\" role=\"presentation\" style=\"width:568px;\" width=\"568\" ><tr><td style=\"line-height:0px;font-size:0px;mso-line-height-rule:exactly;\"><![endif]--><div class=\"asin-grid-custom-border\" style=\"margin:0px auto;max-width:568px;\"><table align=\"center\" border=\"0\" cellpadding=\"0\" cellspacing=\"0\" role=\"presentation\" style=\"width:100%;\"><tbody><tr><td style=\"direction:ltr;font-size:0px;padding:0;text-align:left;\"><!--[if mso | IE]><table role=\"presentation\" border=\"0\" cellpadding=\"0\" cellspacing=\"0\"><tr><td align=\"left\" class=\"\" width=\"568px\" ><![endif]--> <table class=\"rio-table-grid-table\" role=\"list\" width=\"100%\" border=\"0\" style=\"width:100%;font-size:0;line-height:0;mso-line-height-rule:exactly;\"><tr><td class=\"rio-table-grid-td-bg\" role=\"listitem\" valign=\"top\" width=\"49%\" style=\"width:49%;  border-radius:8px; background-color: #f7f7f7 \">    <table role=\"presentation\" style=\"table-layout:fixed;width:100%;max-width:100%;background-color:#f7f7f7;border-radius:8px;\" class=\"asin-container\"><tr><td style=\"padding:0px;\"><table role=\"presentation\" class=\"rio-asin-container-image\" width=\"100%\"><tr><td align=\"center\"><a href=\"https://www.amazon.com/gp/r.html?C=3BEF3T114MSHJ&K=PLA15W5PCRNT&M=urn:rtn:msg:202603240111072e6e5e7d64a94aec9e4b685effc0p0na&R=37SKNE5LI2A3C&T=C&U=https%3A%2F%2Fwww.amazon.com%2Fdp%2FB09TFNQM7Z%2F%3Fref_%3Dpe_101622500_1365358730_AGH_05_00_IMG_05_pd_ot_dealz_cml_2p_0_lm%26%26pd_rd_wg%3DnqoF0%26pd_rd_w%3DqQr2O%26pf_rd_p%3Da8d0e2f2-4440-4d65-ab3e-ecdf4be36c39%26pd_rd_r%3Da40c2ef2-764a-4791-8cf8-7ad898c9710c%26content-id%3Damzn1.sym.a8d0e2f2-4440-4d65-ab3e-ecdf4be36c39&H=PZFYA0TPEK7QFRTLZW11JW87OQAA&ref_=pe_101622500_1365358730_AGH_05_00_IMG_05_pd_ot_dealz_cml_2p_0_lm\" target=\"_blank\"><img src=\"https://m.media-amazon.com/images/I/51PPQK3Hw6L._SR538,538_.jpg\" alt=\"BEGRIM Cat Toy Pointer\" align=\"center\" width=\"269\" height=\"269\" style=\"width: 100%;height: auto;max-width:269px;max-height:269px;\"></a></td></tr></table><div style=\"padding:4px;\">    <mj-raw></mj-raw><table width=\"100%\" style=\"width: 100%;\" role=\"presentation\"><tbody><tr><td style='text-align: left; direction=\"ltr\" !important;'><table style=\"border-spacing: 20px;\" role=\"presentation\"><tr style=\"display: block; padding-bottom: 2px\"><td style=\"text-align: left;\"><span class=\"priceBadge\" style=\"font-weight:700;font-size:11px;line-height:12px;display:block;color:#CC0C39;\">      Limited time deal  </span></td></tr><tr style=\"display: block; padding-bottom: 2px\"><td style=\"text-align: left; height: 24px; padding-right: 6px;\"><span class=\"priceDiscount\" style=\"font-weight:400;font-size:11px;line-height:16px;color:#FFFFFF;background-color:#CC0C39;padding:4px 6px 4px 6px;white-space:nowrap;border-radius:2px;\">-10% </span></td></tr> </table></td></tr></tbody></table><mj-raw></mj-raw></div></td></tr></table></td><td aria-hidden=\"true\" width=\"2%\" style=\"width:2%;\"><div style=\"width:8px\">&nbsp;</div></td>  <td class=\"rio-table-grid-td-bg\" role=\"listitem\" valign=\"top\" width=\"49%\" style=\"width:49%;  border-radius:8px; background-color: #f7f7f7 \">    <table role=\"presentation\" style=\"table-layout:fixed;width:100%;max-width:100%;background-color:#f7f7f7;border-radius:8px;\" class=\"asin-container\"><tr><td style=\"padding:0px;\"><table role=\"presentation\" class=\"rio-asin-container-image\" width=\"100%\"><tr><td align=\"center\"><a href=\"https://www.amazon.com/gp/r.html?C=3BEF3T114MSHJ&K=PLA15W5PCRNT&M=urn:rtn:msg:202603240111072e6e5e7d64a94aec9e4b685effc0p0na&R=1F16NFXLP0N7R&T=C&U=https%3A%2F%2Fwww.amazon.com%2Fdp%2FB01LWPQ4D6%2F%3Fref_%3Dpe_101622500_1365358730_AGH_05_01_IMG_05_pd_ot_dealz_cml_2p_1_lm%26%26pd_rd_wg%3DnqoF0%26pd_rd_w%3DqQr2O%26pf_rd_p%3Da8d0e2f2-4440-4d65-ab3e-ecdf4be36c39%26pd_rd_r%3Da40c2ef2-764a-4791-8cf8-7ad898c9710c%26content-id%3Damzn1.sym.a8d0e2f2-4440-4d65-ab3e-ecdf4be36c39&H=AGLJCRQRK7CYRUNDCQI2XZ8PCOQA&ref_=pe_101622500_1365358730_AGH_05_01_IMG_05_pd_ot_dealz_cml_2p_1_lm\" target=\"_blank\"><img src=\"https://m.media-amazon.com/images/I/41CwH8IkptL._SR538,538_.jpg\" alt=\"Yes4All Foam Roller\" align=\"center\" width=\"269\" height=\"269\" style=\"width: 100%;height: auto;max-width:269px;max-height:269px;\"></a></td></tr></table><div style=\"padding:4px;\">    <mj-raw></mj-raw><table width=\"100%\" style=\"width: 100%;\" role=\"presentation\"><tbody><tr><td style='text-align: left; direction=\"ltr\" !important;'><table style=\"border-spacing: 20px;\" role=\"presentation\"><tr style=\"display: block; padding-bottom: 2px\"><td style=\"text-align: left;\"><span class=\"priceBadge\" style=\"font-weight:700;font-size:11px;line-height:12px;display:block;color:#CC0C39;\">      Limited time deal  </span></td></tr><tr style=\"display: block; padding-bottom: 2px\"><td style=\"text-align: left; height: 24px; padding-right: 6px;\"><span class=\"priceDiscount\" style=\"font-weight:400;font-size:11px;line-height:16px;color:#FFFFFF;background-color:#CC0C39;padding:4px 6px 4px 6px;white-space:nowrap;border-radius:2px;\">-10% </span></td></tr> </table></td></tr></tbody></table><mj-raw></mj-raw></div></td></tr></table></td></tr><tr aria-hidden=\"true\"><td colspan=\"3\" width=\"100%\" height=\"8\" style=\"width:100%; height:8px; line-height:8px; mso-line-height-rule:exactly;\">&nbsp;</td></tr><tr>  <td class=\"rio-table-grid-td-bg\" role=\"listitem\" valign=\"top\" width=\"49%\" style=\"width:49%;  border-radius:8px; background-color: #f7f7f7 \">    <table role=\"presentation\" style=\"table-layout:fixed;width:100%;max-width:100%;background-color:#f7f7f7;border-radius:8px;\" class=\"asin-container\"><tr><td style=\"padding:0px;\"><table role=\"presentation\" class=\"rio-asin-container-image\" width=\"100%\"><tr><td align=\"center\"><a href=\"https://www.amazon.com/gp/r.html?C=3BEF3T114MSHJ&K=PLA15W5PCRNT&M=urn:rtn:msg:202603240111072e6e5e7d64a94aec9e4b685effc0p0na&R=1YQSKJPHL6G0Y&T=C&U=https%3A%2F%2Fwww.amazon.com%2Fdp%2FB00007J5U7%2F%3Fref_%3Dpe_101622500_1365358730_AGH_05_02_IMG_05_pd_ot_dealz_cml_2p_2_lm%26%26pd_rd_wg%3DnqoF0%26pd_rd_w%3DqQr2O%26pf_rd_p%3Da8d0e2f2-4440-4d65-ab3e-ecdf4be36c39%26pd_rd_r%3Da40c2ef2-764a-4791-8cf8-7ad898c9710c%26content-id%3Damzn1.sym.a8d0e2f2-4440-4d65-ab3e-ecdf4be36c39&H=VNWS2KX2ZOFAQJ4XAH5VM0HIGH8A&ref_=pe_101622500_1365358730_AGH_05_02_IMG_05_pd_ot_dealz_cml_2p_2_lm\" target=\"_blank\"><img src=\"https://m.media-amazon.com/images/I/31wuPFARpOS._SR538,538_.jpg\" alt=\"Zojirushi Rice Cooker and Warmer\" align=\"center\" width=\"269\" height=\"269\" style=\"width: 100%;height: auto;max-width:269px;max-height:269px;\"></a></td></tr></table><div style=\"padding:4px;\">    <mj-raw></mj-raw><table width=\"100%\" style=\"width: 100%;\" role=\"presentation\"><tbody><tr><td style='text-align: left; direction=\"ltr\" !important;'><table style=\"border-spacing: 20px;\" role=\"presentation\"><tr style=\"display: block; padding-bottom: 2px\"><td style=\"text-align: left;\"><span class=\"priceBadge\" style=\"font-weight:700;font-size:11px;line-height:12px;display:block;color:#CC0C39;\">      Limited time deal  </span></td></tr><tr style=\"display: block; padding-bottom: 2px\"><td style=\"text-align: left; height: 24px; padding-right: 6px;\"><span class=\"priceDiscount\" style=\"font-weight:400;font-size:11px;line-height:16px;color:#FFFFFF;background-color:#CC0C39;padding:4px 6px 4px 6px;white-space:nowrap;border-radius:2px;\">-18% </span></td></tr> </table></td></tr></tbody></table><mj-raw></mj-raw></div></td></tr></table></td><td aria-hidden=\"true\" width=\"2%\" style=\"width:2%;\"><div style=\"width:8px\">&nbsp;</div></td>  <td class=\"rio-table-grid-td-bg\" role=\"listitem\" valign=\"top\" width=\"49%\" style=\"width:49%;  border-radius:8px; background-color: #f7f7f7 \">    <table role=\"presentation\" style=\"table-layout:fixed;width:100%;max-width:100%;background-color:#f7f7f7;border-radius:8px;\" class=\"asin-container\"><tr><td style=\"padding:0px;\"><table role=\"presentation\" class=\"rio-asin-container-image\" width=\"100%\"><tr><td align=\"center\"><a href=\"https://www.amazon.com/gp/r.html?C=3BEF3T114MSHJ&K=PLA15W5PCRNT&M=urn:rtn:msg:202603240111072e6e5e7d64a94aec9e4b685effc0p0na&R=1VT867O1PE3X&T=C&U=https%3A%2F%2Fwww.amazon.com%2Fdp%2FB0BWTPH7L1%2F%3Fref_%3Dpe_101622500_1365358730_AGH_05_03_IMG_05_pd_ot_dealz_cml_2p_3_lm%26%26pd_rd_wg%3DnqoF0%26pd_rd_w%3DqQr2O%26pf_rd_p%3Da8d0e2f2-4440-4d65-ab3e-ecdf4be36c39%26pd_rd_r%3Da40c2ef2-764a-4791-8cf8-7ad898c9710c%26content-id%3Damzn1.sym.a8d0e2f2-4440-4d65-ab3e-ecdf4be36c39&H=SP29RCTKRG6GNAUNMPW3AZO9GHGA&ref_=pe_101622500_1365358730_AGH_05_03_IMG_05_pd_ot_dealz_cml_2p_3_lm\" target=\"_blank\"><img src=\"https://m.media-amazon.com/images/I/517qKc1ue6L._SR538,538_.jpg\" alt=\"gianotter Desk Organizers and Accessories\" align=\"center\" width=\"269\" height=\"269\" style=\"width: 100%;height: auto;max-width:269px;max-height:269px;\"></a></td></tr></table><div style=\"padding:4px;\">    <mj-raw></mj-raw><table width=\"100%\" style=\"width: 100%;\" role=\"presentation\"><tbody><tr><td style='text-align: left; direction=\"ltr\" !important;'><table style=\"border-spacing: 20px;\" role=\"presentation\"><tr style=\"display: block; padding-bottom: 2px\"><td style=\"text-align: left;\"><span class=\"priceBadge\" style=\"font-weight:700;font-size:11px;line-height:12px;display:block;color:#CC0C39;\">      Limited time deal  </span></td></tr><tr style=\"display: block; padding-bottom: 2px\"><td style=\"text-align: left; height: 24px; padding-right: 6px;\"><span class=\"priceDiscount\" style=\"font-weight:400;font-size:11px;line-height:16px;color:#FFFFFF;background-color:#CC0C39;padding:4px 6px 4px 6px;white-space:nowrap;border-radius:2px;\">-27% </span></td></tr> </table></td></tr></tbody></table><mj-raw></mj-raw></div></td></tr></table></td>   </tr></table><!--[if mso | IE]></td></tr></table><![endif]--></td></tr></tbody></table></div><!--[if mso | IE]></td></tr></table></td></tr></table><![endif]--></td></tr></tbody></table></div><!--[if mso | IE]></td></tr></table></td></tr><![endif]-->   <!--[if mso | IE]></table><![endif]--></td></tr></tbody></table></div><!--[if mso | IE]></td></tr></table><![endif]--> <!--[if mso | IE]><table align=\"center\" border=\"0\" cellpadding=\"0\" cellspacing=\"0\" class=\"rootContent-outlook moduleId-category3by1-outlook\" role=\"presentation\" style=\"width:600px;\" width=\"600\" bgcolor=\"#ffffff\" ><tr><td style=\"line-height:0px;font-size:0px;mso-line-height-rule:exactly;\"><![endif]--><div class=\"rootContent moduleId-category3by1\" style=\"background:#ffffff;background-color:#ffffff;margin:0px auto;max-width:600px;\"><table align=\"center\" border=\"0\" cellpadding=\"0\" cellspacing=\"0\" role=\"presentation\" style=\"background:#ffffff;background-color:#ffffff;width:100%;\"><tbody><tr><td style=\"direction:ltr;font-size:0px;padding:4px 8px 4px 8px;text-align:left;\"><!--[if mso | IE]><table role=\"presentation\" border=\"0\" cellpadding=\"0\" cellspacing=\"0\"><![endif]-->    <!--[if mso | IE]><tr><td align=\"left\" class=\"sonar-category-row-hve-outlook sonar-category-row-hve-v1-outlook\" width=\"600px\" ><table align=\"center\" border=\"0\" cellpadding=\"0\" cellspacing=\"0\" class=\"rio-card-outlook\" role=\"presentation\" style=\"width:584px;\" width=\"584\" bgcolor=\"#ffffff\" ><tr><td style=\"line-height:0px;font-size:0px;mso-line-height-rule:exactly;\"><![endif]--><div class=\"rio-card\" style=\"background:#ffffff;background-color:#ffffff;margin:0px auto;border-radius:4px;max-width:584px;\"><table align=\"center\" border=\"0\" cellpadding=\"0\" cellspacing=\"0\" role=\"presentation\" style=\"background:#ffffff;background-color:#ffffff;width:100%;border-radius:4px;\"><tbody><tr><td style=\"direction:ltr;font-size:0px;padding:4px 8px 4px 8px;text-align:left;\"><!--[if mso | IE]><table role=\"presentation\" border=\"0\" cellpadding=\"0\" cellspacing=\"0\"><tr><td align=\"left\" class=\"\" width=\"584px\" ><![endif]-->  <table cellpadding=\"0\" cellspacing=\"0\" role=\"presentation\" width=\"100%\" border=\"0\" style=\"color:#000000;font-family:Ember,'Amazon Ember',Arial,sans-serif;font-size:15px;line-height:22px;table-layout:auto;width:100%;border:none;\"><tr><td width=\"65%\"><div style=\"font-family:Ember,'Amazon Ember',Arial,sans-serif;font-size:15px;line-height:1;text-align:left;color:#000000;\"><h2 style=\"margin:0;padding:0;font-family:Ember,'Amazon Ember',Arial,sans-serif;font-weight:700;font-size:18px;line-height:22px;color:#0F1111;\" class=\"rio-header rio-header-594\">Shop deals by price</h2></div></td></tr></table><div aria-hidden=\"true\" style=\"height:8px;line-height:8px\">&nbsp;</div><!--[if mso | IE]></td></tr><tr><td align=\"left\" class=\"\" width=\"584px\" ><![endif]--> <table class=\"rio-table-grid-table\" role=\"list\" width=\"100%\" border=\"0\" style=\"width:100%;font-size:0;line-height:0;mso-line-height-rule:exactly;\"><tr>  <td class=\"\" role=\"listitem\" valign=\"top\" width=\"32%\" style=\"width:32%; \">     <a href=\"https://www.amazon.com/gp/r.html?C=3BEF3T114MSHJ&K=PLA15W5PCRNT&M=urn:rtn:msg:202603240111072e6e5e7d64a94aec9e4b685effc0p0na&R=3L8H5SQ7FJ521&T=C&U=https%3A%2F%2Fwww.amazon.com%2Fdeals%3Fdiscounts-widget%3D%252522%25257B%25255C%252522state%25255C%252522%25253A%25257B%25255C%252522rangeRefinementFilters%25255C%252522%25253A%25257B%25255C%252522price%25255C%252522%25253A%25257B%25255C%252522min%25255C%252522%25253A0%25252C%25255C%252522max%25255C%252522%25253A10%25257D%25257D%25257D%25252C%25255C%252522version%25255C%252522%25253A1%25257D%252522%26promotionsSearchLastSeenAsin%3DB0B6CMT476%26promotionsSearchStartIndex%3D0%26promotionsSearchPageSize%3D60%26ref_%3Dpe_101622500_1365358730_CRH_06_00_IMG_06&H=OFPA65UYOSOWCQLPZASJJAFO7LYA&ref_=pe_101622500_1365358730_CRH_06_00_IMG_06\" target=\"_blank\"> <img width=\"184\" src=\"https://m.media-amazon.com/images/G/01/Outbound/2026/EvergreenEmails/Deals/Library-Text-Only/AME_Evergreen_Deals_Email_CatRow_10_545x400.png\" alt=\"Under $10\" align=\"center\" style=\"width:100%;max-width:184px;display:block;border-radius:8px;\"> </a>    </td><td aria-hidden=\"true\" width=\"2%\" style=\"width:2%;\"><div style=\"width:8px\">&nbsp;</div></td>    <td class=\"\" role=\"listitem\" valign=\"top\" width=\"32%\" style=\"width:32%; \">     <a href=\"https://www.amazon.com/gp/r.html?C=3BEF3T114MSHJ&K=PLA15W5PCRNT&M=urn:rtn:msg:202603240111072e6e5e7d64a94aec9e4b685effc0p0na&R=26KAYPGW0KTQB&T=C&U=https%3A%2F%2Fwww.amazon.com%2Fdeals%3Fdiscounts-widget%3D%252522%25257B%25255C%252522state%25255C%252522%25253A%25257B%25255C%252522rangeRefinementFilters%25255C%252522%25253A%25257B%25255C%252522price%25255C%252522%25253A%25257B%25255C%252522min%25255C%252522%25253A0%25252C%25255C%252522max%25255C%252522%25253A20%25257D%25257D%25257D%25252C%25255C%252522version%25255C%252522%25253A1%25257D%252522%26ref_%3Dpe_101622500_1365358730_CRH_06_01_IMG_06&H=47XG92HBK4VWTIVYHZHUDUUMA78A&ref_=pe_101622500_1365358730_CRH_06_01_IMG_06\" target=\"_blank\"> <img width=\"184\" src=\"https://m.media-amazon.com/images/G/01/Outbound/2026/EvergreenEmails/Deals/Library-Text-Only/AME_Evergreen_Deals_3-9_Email_3B_CatRow_20_545x400.png\" alt=\"Under $20\" align=\"center\" style=\"width:100%;max-width:184px;display:block;border-radius:8px;\"> </a>    </td><td aria-hidden=\"true\" width=\"2%\" style=\"width:2%;\"><div style=\"width:8px\">&nbsp;</div></td>    <td class=\"\" role=\"listitem\" valign=\"top\" width=\"32%\" style=\"width:32%; \">     <a href=\"https://www.amazon.com/gp/r.html?C=3BEF3T114MSHJ&K=PLA15W5PCRNT&M=urn:rtn:msg:202603240111072e6e5e7d64a94aec9e4b685effc0p0na&R=2WX267N0PZ580&T=C&U=https%3A%2F%2Fwww.amazon.com%2Fdeals%3Fdiscounts-widget%3D%252522%25257B%25255C%252522state%25255C%252522%25253A%25257B%25255C%252522rangeRefinementFilters%25255C%252522%25253A%25257B%25255C%252522price%25255C%252522%25253A%25257B%25255C%252522min%25255C%252522%25253A0%25252C%25255C%252522max%25255C%252522%25253A30%25257D%25257D%25257D%25252C%25255C%252522version%25255C%252522%25253A1%25257D%252522%26ref_%3Dpe_101622500_1365358730_CRH_06_02_IMG_06&H=DLYJRMYXUAD0A0ACSK8NG1G1OE0A&ref_=pe_101622500_1365358730_CRH_06_02_IMG_06\" target=\"_blank\"> <img width=\"184\" src=\"https://m.media-amazon.com/images/G/01/Outbound/2026/EvergreenEmails/Deals/Library-Text-Only/AME_Evergreen_Deals_3-9_Email_3C_CatRow_30_545x400.png\" alt=\"Under $30\" align=\"center\" style=\"width:100%;max-width:184px;display:block;border-radius:8px;\"> </a>    </td>    </tr></table><!--[if mso | IE]></td></tr></table><![endif]--></td></tr></tbody></table></div><!--[if mso | IE]></td></tr></table></td></tr><![endif]--> <!--[if mso | IE]></table><![endif]--></td></tr></tbody></table></div><!--[if mso | IE]></td></tr></table><![endif]--> <!--[if mso | IE]><table align=\"center\" border=\"0\" cellpadding=\"0\" cellspacing=\"0\" class=\"rootContent-outlook moduleId-legalFooter-outlook\" role=\"presentation\" style=\"width:600px;\" width=\"600\" bgcolor=\"#ffffff\" ><tr><td style=\"line-height:0px;font-size:0px;mso-line-height-rule:exactly;\"><![endif]--><div class=\"rootContent moduleId-legalFooter\" style=\"background:#ffffff;background-color:#ffffff;margin:0px auto;max-width:600px;\"><table align=\"center\" border=\"0\" cellpadding=\"0\" cellspacing=\"0\" role=\"presentation\" style=\"background:#ffffff;background-color:#ffffff;width:100%;\"><tbody><tr><td style=\"direction:ltr;font-size:0px;padding:4px 0px 0px 0px;text-align:left;\"><!--[if mso | IE]><table role=\"presentation\" border=\"0\" cellpadding=\"0\" cellspacing=\"0\"><![endif]--> <!--[if mso | IE]><tr><td align=\"left\" class=\"sonar-footer-outlook sonar-footer-v1-outlook\" width=\"600px\" ><![endif]--><style type=\"text/css\">.footer-text, .footer-card p, .footer-card li {\r\n            color: #494D4D;\r\n        }\r\n        .footer-card p{margin-top:20px}\r\n        .footer-card a {\r\n            color: #007185 !important;\r\n            text-decoration: none !important;\r\n        }\r\n        @media (prefers-color-scheme:dark){\r\n            .footer-card {\r\n                background-color: #303333 !important;\r\n            }\r\n            \r\n            .footer-card a {\r\n                color: #6ED6E6 !important;\r\n            }\r\n            \r\n            .footer-text, .footer-card p, .footer-card li {\r\n                color: #C8CCCC !important;\r\n            }\r\n            .lightFooterImg{display:none!important}.darkFooterImg{display:block!important}}[data-ogsb] .footer-card{background-color:#303333!important}\r\n        [data-ogsc] .footer-card a {\r\n            color: #6ED6E6 !important;\r\n        }\r\n        [data-ogsc] .footer-card li,[data-ogsc] .footer-card p,[data-ogsc] .footer-text{color:#c8cccc!important}[data-ogsc] .lightFooterImg{display:none!important}[data-ogsc] .darkFooterImg{display:block!important}</style><table class=\"footer-card\" data-sonar-role=\"footer\" width=\"100%\" cellspacing=\"0\" cellpadding=\"0\" border=\"0\" role=\"presentation\" style=\"background-color:#F0F2F2;width:100%;\"><tr><td width=\"100%\" align=\"left\" style=\"width:100%;padding-bottom:4px;text-align:left\"><table width=\"100%\" cellspacing=\"0\" cellpadding=\"0\" border=\"0\" role=\"presentation\" style=\"width:100%;\"><tr><td class=\"footer-text\" style=\"width:100%;padding:0 16px 16px 16px;font-family:Ember,'Amazon Ember',Arial,sans-serif;font-size:14px;line-height:20px;color:#494D4D;\"><div style=\"margin-top:16px;\"><a href=\"https://www.amazon.com/gp/r.html?C=3BEF3T114MSHJ&K=PLA15W5PCRNT&M=urn:rtn:msg:202603240111072e6e5e7d64a94aec9e4b685effc0p0na&R=2CDI56SJ5VTQ&T=C&U=https%3A%2F%2Fwww.amazon.com%2Fgp%2Fcpc%2Fhomepage%3Fref_%3Dpe_101622500_1365358730_LF_07_01_LNK_07_pe_ob_ftr_comm_prfs&H=D27EKKA4I98ALZZDWAK7FC9VNCGA&ref_=pe_101622500_1365358730_LF_07_01_LNK_07_pe_ob_ftr_comm_prfs\" target=\"_blank\" style=\"color:#007185;text-decoration:none;\">Update your preferences </a>&nbsp;&nbsp;|&nbsp;&nbsp;<a href=\"https://www.amazon.com/gp/r.html?C=3BEF3T114MSHJ&K=PLA15W5PCRNT&M=urn:rtn:msg:202603240111072e6e5e7d64a94aec9e4b685effc0p0na&R=1XWYT4DX38XJB&T=X&U=https%3A%2F%2Fwww.amazon.com%2Fgp%2Fgss%2Fo%2F10Nt6CRxlYLKHVArDD0tYCvrBz7X8eJGyaFUiO4DHMTzSuM3sj9g6iHGOh-hTCndJ%3Fref_%3DLF_07_02_LNK_07&H=5O8ROQPCSSSRAYGOYDKMJ5NAZDYA\" target=\"_blank\" style=\"color:#007185;text-decoration:none;\"> Unsubscribe</a></div><div style=\"margin-top:20px;\">©2026 Amazon.com, Inc. or its affiliates. Amazon and all related marks are trademarks of Amazon.com, Inc. or its affiliates, Amazon.com 410 Terry Avenue N., Seattle, WA 98109. Product prices and availability are subject to change. Ref: 1365358730.</div> <div style=\"margin-top:20px;\"> <a href=\"https://www.amazon.com/gp/r.html?C=3BEF3T114MSHJ&K=PLA15W5PCRNT&M=urn:rtn:msg:202603240111072e6e5e7d64a94aec9e4b685effc0p0na&R=3UXP83NM7LX0&T=C&U=https%3A%2F%2Fwww.amazon.com%2Fgp%2Fhelp%2Fcustomer%2Fdisplay.html%3FnodeId%3D468496%26ref_%3Dpe_101622500_1365358730_LF_07_03_LNK_07&H=9VJPNBIXAR5YXOAJVAAQQ186VX0A&ref_=pe_101622500_1365358730_LF_07_03_LNK_07\" target=\"_blank\" style=\"color:#007185;text-decoration:none;\">Privacy Notice </a></div></td></tr></table><a href=\"https://www.amazon.com/gp/r.html?C=3BEF3T114MSHJ&K=PLA15W5PCRNT&M=urn:rtn:msg:202603240111072e6e5e7d64a94aec9e4b685effc0p0na&R=17NFN3AYZDUP1&T=C&U=https%3A%2F%2Fwww.amazon.com%3Fref_%3Dpe_101622500_1365358730_LF_07_04_LNK_07&H=ELBFMBVBLX4CFPMPTUM4OOYG27GA&ref_=pe_101622500_1365358730_LF_07_04_LNK_07\" target=\"_blank\"><img src=\"https://m.media-amazon.com/images/G/01/outbound/OutboundTemplates/Smile_Logo_Light._BG240,242,242_.png\" alt=\"Amazon.com\" height=\"43\" width=\"86\" align=\"left\" class=\"lightFooterImg\" style=\"display:block;\"> <!--[if !mso]><! --><img src=\"https://m.media-amazon.com/images/G/01/outbound/OutboundTemplates/Smile_Logo_Dark.png\" alt=\"Amazon.com\" height=\"43\" width=\"86\" align=\"left\" class=\"darkFooterImg\" style=\"display:none;\"><!--<![endif]--></a></td></tr></table><!--[if mso | IE]></td></tr><![endif]--> <!--[if mso | IE]></table><![endif]--></td></tr></tbody></table></div><!--[if mso | IE]></td></tr></table><![endif]--></div><img width=\"1\" height=\"1\" src=\"https://www.amazon.com/gp/r.html?C=3BEF3T114MSHJ&K=PLA15W5PCRNT&M=urn:rtn:msg:202603240111072e6e5e7d64a94aec9e4b685effc0p0na&R=1J35IB0QUWJPQ&T=E&U=https%3A%2F%2Fimages-na.ssl-images-amazon.com%2Fimages%2FG%2F01%2Fnav%2Ftransp.gif&H=Z9KQCEBQNDXQACIAWJ5OBVQYIY8A&ref_=pe_101622500_1365358730_open\" alt=\"\" /></body></html>",
  "attachments": [],
  "headers": {
    "Delivered-To": "starworks5@gmail.com",
    "Received": "from a15-108.smtp-out.amazonses.com (a15-108.smtp-out.amazonses.com. [54.240.15.108])        by mx.google.com with ESMTPS id 6a1803df08f44-89c85387569si168569346d6.616.2026.03.23.18.11.09        for <starworks5@gmail.com>        (version=TLS1_3 cipher=TLS_AES_128_GCM_SHA256 bits=128/128);        Mon, 23 Mar 2026 18:11:09 -0700 (PDT)",
    "X-Received": "by 2002:a05:622a:59c5:b0:509:820:58d7 with SMTP id d75a77b69052e-50b37515223mr217547951cf.52.1774314669426;        Mon, 23 Mar 2026 18:11:09 -0700 (PDT)",
    "ARC-Seal": "i=1; a=rsa-sha256; t=1774314669; cv=none;        d=google.com; s=arc-20240605;        b=FokMCllV1eypjnRUV7JIJH0Ysh2rHkI5PzKPvHNdHKqn358zG1kOvtsXgOdpoT2u+w         ceiC61PmH10ZOdQAxj6lKsUhcbF2XPZWqFLRfBUbL8N8Pjx2A7PVQRa5VoTdISwIt6kZ         NCPnxbkIggtsMUhxsNMnOl1IhIWAYW7FE9y6LdB6Vrv9+t981klJ3Rz7A3SHG2q6iefz         S8Ia8tY+5MXluGF2T+P0Z3VHDAF2odfxPDr2QzC6xtsUpjVAHlo5nXtz9Bd9kIlyfVHi         MkqHkRHYXCMe8VFqPnjWErgY+EdaNLnGeXZ0FlV8FzgyoJxP3xr0uJ/7GjzIqNV7w/IZ         bZEw==",
    "ARC-Message-Signature": "i=1; a=rsa-sha256; c=relaxed/relaxed; d=google.com; s=arc-20240605;        h=feedback-id:list-unsubscribe:list-unsubscribe-post:bounces-to         :mime-version:subject:message-id:to:from:date:dkim-signature         :dkim-signature;        bh=fFEDLa+DcYb3/MPrUhmZ6sxdIOc6xJg3GwJ9hTlTwQw=;        fh=gPPrbYv6bjiCeSNOMtV7+ATcg7xOVeWRNeqU1P80kc4=;        b=d3tLOAiYGeQabfQEM8XFkUr/DHmLi88P2FOWDhnAJ/iXZ8b57nP6iuLb+Ob9eIIL58         kXQFsf4uOSErrhuzKrhSdiipk6ucdlL0TV6sH51j4Wik4QoFlPqPdDZ3HENQQuTc14ei         vOFkWRnNk5B11GKOtMKfEbMloRloiEr8OuGpwuurkEyjNEouo17dda6uBeWqNQbnoT3e         G+RsmCm3/QndUfWlnSwSFv4dLQ3/LN1OuFUwnnTIj+QFcV65RU1f36nVgipgbGh03hVQ         RjxdsXmegZ3cSkKoQwdRidZAPAOdYubAKLQSqvLJs+suY/8DjefnTEWuZ+OPLiwXljiZ         xOyg==;        dara=google.com",
    "ARC-Authentication-Results": "i=1; mx.google.com;       dkim=pass header.i=@amazon.com header.s=taugkdi5ljtmsua4uibbmo5mda3r2q3v header.b=cqRTBQNZ;       dkim=pass header.i=@amazonses.com header.s=224i4yxa5dv7c2xz3womw6peuasteono header.b=AwQ1pzcj;       spf=pass (google.com: domain of 202603240111072e6e5e7d64a94aec9e4b685effc0p0na-c3wfplh2un6ms@bounces.amazon.com designates 54.240.15.108 as permitted sender) smtp.mailfrom=202603240111072e6e5e7d64a94aec9e4b685effc0p0na-C3WFPLH2UN6MS@bounces.amazon.com;       dmarc=pass (p=QUARANTINE sp=QUARANTINE dis=NONE) header.from=amazon.com",
    "Return-Path": "<202603240111072e6e5e7d64a94aec9e4b685effc0p0na-C3WFPLH2UN6MS@bounces.amazon.com>",
    "Received-SPF": "pass (google.com: domain of 202603240111072e6e5e7d64a94aec9e4b685effc0p0na-c3wfplh2un6ms@bounces.amazon.com designates 54.240.15.108 as permitted sender) client-ip=54.240.15.108;",
    "Authentication-Results": "mx.google.com;       dkim=pass header.i=@amazon.com header.s=taugkdi5ljtmsua4uibbmo5mda3r2q3v header.b=cqRTBQNZ;       dkim=pass header.i=@amazonses.com header.s=224i4yxa5dv7c2xz3womw6peuasteono header.b=AwQ1pzcj;       spf=pass (google.com: domain of 202603240111072e6e5e7d64a94aec9e4b685effc0p0na-c3wfplh2un6ms@bounces.amazon.com designates 54.240.15.108 as permitted sender) smtp.mailfrom=202603240111072e6e5e7d64a94aec9e4b685effc0p0na-C3WFPLH2UN6MS@bounces.amazon.com;       dmarc=pass (p=QUARANTINE sp=QUARANTINE dis=NONE) header.from=amazon.com",
    "DKIM-Signature": "v=1; a=rsa-sha256; q=dns/txt; c=relaxed/simple;\ts=224i4yxa5dv7c2xz3womw6peuasteono; d=amazonses.com; t=1774314669;\th=Date:From:To:Message-ID:Subject:MIME-Version:Content-Type:List-Unsubscribe-Post:List-Unsubscribe:Feedback-ID;\tbh=26zbSfd/P26yWlCufuOwLHQMCRS9F0zrCOwPaaQaP64=;\tb=AwQ1pzcjHXxw3nTZRB/ATs/YswfOdyrrATLMgiljurjdJ/A+qwfnv5agSo++1U81\tDd0cU+k75heFXvmOxSMyn07nZ9TuQLyqflrozHWfYzhomyacyDI2aBlPGPFM3tH9VOM\t9RsDhtlAkLroGn3+VszLNNaMlNrbHPJQCuwAMRPc=",
    "Date": "Tue, 24 Mar 2026 01:11:09 +0000",
    "From": "\"Amazon.com\" <store-news@amazon.com>",
    "To": "starworks5@gmail.com",
    "Message-ID": "<0100019d1d6543f5-b15cc0a9-79b2-4bc3-b2f7-abd2f20694b4-000000@email.amazonses.com>",
    "Subject": "Today’s deals, curated for you",
    "MIME-Version": "1.0",
    "Content-Type": "multipart/alternative; boundary=\"----=_Part_8765542_1176692806.1774314669033\"",
    "X-AMAZON-MAIL-RELAY-TYPE": "notification",
    "Bounces-to": "202603240111072e6e5e7d64a94aec9e4b685effc0p0na-C3WFPLH2UN6MS@bounces.amazon.com",
    "X-AMAZON-METADATA": "CA=C3WFPLH2UN6MS-CU=A2FZZGZKRJZ0A0",
    "List-Unsubscribe-Post": "List-Unsubscribe=One-Click",
    "List-Unsubscribe": "<https://www.amazon.com/gp/r.html?C=3BEF3T114MSHJ&K=PLA15W5PCRNT&M=urn:rtn:msg:202603240111072e6e5e7d64a94aec9e4b685effc0p0na&R=1XWYT4DX38XJB&T=X&U=https%3A%2F%2Fwww.amazon.com%2Fgp%2Fgss%2Fo%2F10Nt6CRxlYLKHVArDD0tYCvrBz7X8eJGyaFUiO4DHMTzSuM3sj9g6iHGOh-hTCndJ%3Fref_%3DLF_07_02_LNK_07&H=5O8ROQPCSSSRAYGOYDKMJ5NAZDYA>",
    "X-Original-MessageID": "<urn.rtn.msg.202603240111072e6e5e7d64a94aec9e4b685effc0p0na@1774314669035.>",
    "Feedback-ID": "1365358730::1.us-east-1.+gzE1S+MWTFXXYmwxo7wkk651GMxMPAUFYiyN/09X40=:AmazonSES",
    "X-SES-Outgoing": "2026.03.24-54.240.15.108"
  },
  "message_id_header": "<0100019d1d6543f5-b15cc0a9-79b2-4bc3-b2f7-abd2f20694b4-000000@email.amazonses.com>",
  "in_reply_to": "",
  "references": ""
}