{
  "title": "evidence upload report",
  "relative_path": "research_results/grounded_runs/demo_grounded_run_v2/evidence_upload_report.json",
  "source_type": "repository_evidence",
  "filename": "evidence_upload_report.json",
  "mime_type": "application/json",
  "size": 215971,
  "backend_available": true,
  "parser_version": "documents-adapter:1",
  "source": "file",
  "chunk_count": 224,
  "paragraph_count": 1,
  "text_length": 178747,
  "input_format": "text",
  "page_count": 1,
  "extraction_method": "text_normalization",
  "parse_quality": {
    "quality_score": 98.0,
    "quality_tier": "high",
    "quality_flags": [],
    "ocr_used": false
  },
  "source_span": {
    "char_start": 0,
    "char_end": 178747,
    "text_length": 178747,
    "raw_size": 215971,
    "page_count": 1
  },
  "transform_lineage": {
    "source": "file",
    "parser_version": "documents-adapter:1",
    "input_format": "text",
    "normalization": "text_normalization",
    "chunking": {
      "chunk_size": 1000,
      "overlap": 100,
      "chunk_count": 224
    },
    "extraction": {
      "method": "text_normalization",
      "ocr_used": false,
      "page_count": 1
    },
    "source_span": {
      "char_start": 0,
      "char_end": 178747,
      "text_length": 178747,
      "raw_size": 215971,
      "page_count": 1
    }
  },
  "operation": "parse_document_text",
  "provider": "ipfs_datasets_py",
  "implementation_status": "implemented",
  "details": {
    "operation": "parse_document_text",
    "backend_available": true,
    "implementation_status": "implemented"
  },
  "record_id": "18ef79358ea19554df5dc8cf3e52d8cd",
  "checksum": "683e16c641636145760f5e3928337f3537df45faab9fba2ac2d26ec7642a9758",
  "source_path": "/home/barberb/HACC/research_results/grounded_runs/demo_grounded_run_v2/evidence_upload_report.json",
  "parsed_text_path": "/home/barberb/HACC/research_results/documents/repository_ingest/18ef79358ea19554df5dc8cf3e52d8cd.txt",
  "content_type": "application/json",
  "ocr_attempted": false,
  "ocr_used": false,
  "needs_ocr": false
}