{
  "generated_at": "2026-03-17T23:39:48.901313+00:00",
  "preset": "core_hacc_policies",
  "session_id": "session_20260317_233905_000",
  "filing_forum": "court",
  "summary": "If HACC denies a request for an accommodation because it is not reasonable (it would impose an undue financial and administrative burden or fundamentally alter the nature of HACC\u2019s operations), HACC will notify the family in writing of its decision. The notice will inform the family of the right to appeal HACC\u2019s decision through an informal hearing (if ap...",
  "outstanding_intake_gaps": [],
  "follow_up_items": []
}